Workbook

Sheet Risicoprofiel bepalen - bron
D1: RISICOPROFIEL BEPALEN PARTICULIER
A3: Naam : | F3: Punten | H3: Punten
A4: Adres : | H4: te behalen
A5: Woonplaats :
B7: 1 | D7: Wat is uw beleggingsdoelstelling ?
U8: 1 | V8: =CONCATENATE(Y8,Z8) -> 100RM zeer defensieve belegger | Y8: 100RM | Z8: zeer defensieve belegger
B9: 1 | C9: A | D9: Vermogensgroei of vermogensbehoud met een bepaald doelvermogen | E9: X | F9: =IF($E9="X",+$H9,0) -> 2 | H9: 2 | T9: X | U9: 2 | V9: =CONCATENATE(Y9,Z9) -> 100RM zeer defensieve belegger | W9: 3 | Y9: 100RM | Z9: zeer defensieve belegger
B10: 1 | C10: B | D10: Vermogensgroei of vermogensbehoud zonder een bepaald doelvermogen | E10: 0 | F10: =IF($E10="X",+$H10,0) -> 0 | H10: 3 | T10: 0 | U10: 3 | V10: =CONCATENATE(Y10,Z10) -> 20RD80RM Defensieve belegger | Y10: 20RD80RM | Z10: Defensieve belegger
B11: 1 | C11: C | D11: Jaarlijkse aanvulling op het huidige inkomen | E11: 0 | F11: =IF($E11="X",+$H11,0) -> 0 | H11: 0 | U11: 4 | V11: =CONCATENATE(Y11,Z11) -> 20RD80RM Defensieve belegger | Y11: 20RD80RM | Z11: Defensieve belegger
B12: 1 | C12: D | D12: Financiering van een toekomstige uitgave, bv de studie van kinderen, of eerder stoppen met werken | E12: 0 | F12: =IF($E12="X",+$H12,0) -> 0 | H12: 1 | U12: 5 | V12: =CONCATENATE(Y12,Z12) -> 20RD80RM Defensieve belegger | Y12: 20RD80RM | Z12: Defensieve belegger
B14: 2 | D14: Bent U van plan tussentijds vermogen aan uw beleggingsportefeuille te onttrekken of juist vervolgstortingen te doen ? | U14: 6 | V14: =CONCATENATE(Y14,Z14) -> 20RD80RM Defensieve belegger | Y14: 20RD80RM | Z14: Defensieve belegger
D15: Ik ben van plan:
B17: 2 | C17: A | D17: Periodiek te onttrekken | E17: 0 | F17: =IF($E17="X",+$H17,0) -> 0 | H17: 0 | U17: 7 | V17: =CONCATENATE(Y17,Z17) -> 20RD80RM Defensieve belegger | W17: 6 | Y17: 20RD80RM | Z17: Defensieve belegger
B18: 2 | C18: B | D18: Periodiek bij te storten | E18: 0 | F18: =IF($E18="X",+$H18,0) -> 0 | H18: 6 | U18: 8 | V18: =CONCATENATE(Y18,Z18) -> 20RD80RM Defensieve belegger | Y18: 20RD80RM | Z18: Defensieve belegger
B19: 2 | C19: C | D19: Incidenteel te onttrekken | E19: X | F19: =IF($E19="X",+$H19,0) -> 2 | H19: 2 | U19: 9 | V19: =CONCATENATE(Y19,Z19) -> 30RD70RM Gematigd Defensieve belegger | Y19: 30RD70RM | Z19: Gematigd Defensieve belegger
B20: 2 | C20: D | D20: Incidenteel bij te storten | E20: 0 | F20: =IF($E20="X",+$H20,0) -> 0 | H20: 4 | U20: 10 | V20: =CONCATENATE(Y20,Z20) -> 30RD70RM Gematigd Defensieve belegger | Y20: 30RD70RM | Z20: Gematigd Defensieve belegger
B21: 2 | C21: E | D21: Geen of een combinatie van bovenstaande mogelijkheden | E21: 0 | F21: =IF($E21="X",+$H21,0) -> 0 | H21: 3 | U21: 11 | V21: =CONCATENATE(Y21,Z21) -> 30RD70RM Gematigd Defensieve belegger | Y21: 30RD70RM | Z21: Gematigd Defensieve belegger
B23: 3 | D23: Welke gevolgen heeft het niet halen van uw beleggingsdoelstellingen ? | U23: 12 | V23: =CONCATENATE(Y23,Z23) -> 30RD70RM Gematigd Defensieve belegger | W23: 4 | Y23: 30RD70RM | Z23: Gematigd Defensieve belegger
B25: 3 | C25: A | D25: Dit heeft noch financiële, noch emotionele gevolgen | E25: 0 | F25: =IF($E25="X",+$H25,0) -> 0 | H25: 3 | U25: 13 | V25: =CONCATENATE(Y25,Z25) -> 40RD60RM Neutrale Defensieve belegger | Y25: 40RD60RM | Z25: Neutrale Defensieve belegger
B26: 3 | C26: B | D26: Dit zou grote financiële en emotionele consequenties hebben | E26: 0 | F26: =IF($E26="X",+$H26,0) -> 0 | H26: 0 | U26: 14 | V26: =CONCATENATE(Y26,Z26) -> 40RD60RM Neutrale Defensieve belegger | Y26: 40RD60RM | Z26: Neutrale Defensieve belegger
B27: 3 | C27: C | D27: Ik zou teleurgesteld zijn, maar het zou nauwelijks invloed hebben op mijn levenspeil | E27: X | F27: =IF($E27="X",+$H27,0) -> 2 | H27: 2 | U27: 15 | V27: =CONCATENATE(Y27,Z27) -> 40RD60RM Neutrale Defensieve belegger | Y27: 40RD60RM | Z27: Neutrale Defensieve belegger
B28: 3 | C28: D | D28: Ik zou mijn levensstandaard moeten aanpassen | E28: 0 | F28: =IF($E28="X",+$H28,0) -> 0 | H28: 1 | U28: 16 | V28: =CONCATENATE(Y28,Z28) -> 40RD60RM Neutrale Defensieve belegger | Y28: 40RD60RM | Z28: Neutrale Defensieve belegger
B29: 3 | C29: E | D29: Dit zou gevolgen hebben voor………………………. | E29: 0 | F29: =IF($E29="X",+$H29,0) -> 0 | H29: 1
B31: 4 | D31: Welk deel van uw vrij beschikbare vermogen (exclusief de eigen woning) is of wordt belegd op de rekening die wordt beheerd door B.A. van Doorn Comp ? | U31: 17 | V31: =CONCATENATE(Y31,Z31) -> 40RD60RM Neutrale Defensieve belegger | Y31: 40RD60RM | Z31: Neutrale Defensieve belegger
B33: 4 | C33: A | D33: Meer dan 75% | E33: X | F33: =IF($E33="X",+$H33,0) -> 0 | H33: 0 | U33: 18 | V33: =CONCATENATE(Y33,Z33) -> 40RD60RM Neutrale Defensieve belegger | W33: 6 | Y33: 40RD60RM | Z33: Neutrale Defensieve belegger
B34: 4 | C34: B | D34: 50% - 75% | E34: 0 | F34: =IF($E34="X",+$H34,0) -> 0 | H34: 1 | U34: 19 | V34: =CONCATENATE(Y34,Z34) -> 50RD50RM Neutrale belegger | Y34: 50RD50RM | Z34: Neutrale belegger
B35: 4 | C35: C | D35: 25% - 50% | E35: 0 | F35: =IF($E35="X",+$H35,0) -> 0 | H35: 2 | U35: 20 | V35: =CONCATENATE(Y35,Z35) -> 50RD50RM Neutrale belegger | Y35: 50RD50RM | Z35: Neutrale belegger
B36: 4 | C36: D | D36: Minder dan 25% | E36: 0 | F36: =IF($E36="X",+$H36,0) -> 0 | H36: 3 | U36: 21 | V36: =CONCATENATE(Y36,Z36) -> 50RD50RM Neutrale belegger | Y36: 50RD50RM | Z36: Neutrale belegger
B38: 5 | D38: Uw huidige inkomen (uit loon, pensioen onderneming ed) is :
U39: 22 | V39: =CONCATENATE(Y39,Z39) -> 50RD50RM Neutrale belegger | Y39: 50RD50RM | Z39: Neutrale belegger
B40: 5 | C40: A | D40: Onvoldoende om uw vaste lasten en kosten van levensonderhoud te betalen. U komt maandelijks geld tekort. | E40: 0 | F40: =IF($E40="X",+$H40,0) -> 0 | H40: 0 | U40: 23 | V40: =CONCATENATE(Y40,Z40) -> 50RD50RM Neutrale belegger | W40: 8 | Y40: 50RD50RM | Z40: Neutrale belegger
B41: 5 | C41: B | D41: Soms voldoende, soms onvoldoende. Aan het eind van het jaar komt u ongeveer uit. | E41: X | F41: =IF($E41="X",+$H41,0) -> 2 | H41: 2 | U41: 24 | V41: =CONCATENATE(Y41,Z41) -> 50RD50RM Neutrale belegger | Y41: 50RD50RM | Z41: Neutrale belegger
B42: 5 | C42: C | D42: Voldoende om uw vaste lasten en kosten van levensonderhoud te betalen. U kunt maandelijks een bedrag opzij zetten. | E42: 0 | F42: =IF($E42="X",+$H42,0) -> 0 | H42: 4 | U42: 25 | V42: =CONCATENATE(Y42,Z42) -> 50RD50RM Neutrale belegger | Y42: 50RD50RM | Z42: Neutrale belegger
B43: 5 | C43: D | D43: Ruim voldoende om uw vaste lasten en kosten van levensonderhoud te betalen. | E43: 0 | F43: =IF($E43="X",+$H43,0) -> 0 | H43: 6 | U43: 26 | V43: =CONCATENATE(Y43,Z43) -> 50RD50RM Neutrale belegger | Y43: 50RD50RM | Z43: Neutrale belegger
B44: 5 | C44: E | D44: Voldoende om maandelijks een aanzienlijk bedrag opzij te zetten. | E44: 0 | F44: =IF($E44="X",+$H44,0) -> 0 | H44: 8 | U44: 27 | V44: =CONCATENATE(Y44,Z44) -> 60RD40RM Neutrale offensiefe belegger | Y44: 60RD40RM | Z44: Neutrale offensiefe belegger
B47: 6 | D47: Welke kansverdeling spreekt u het meest aan voor het door U te beleggen vermogen ? | U47: 28 | V47: =CONCATENATE(Y47,Z47) -> 60RD40RM Neutrale offensiefe belegger | Y47: 60RD40RM | Z47: Neutrale offensiefe belegger
B49: 6 | C49: A | D49: Een gemiddeld rendement van 6%, maar in een slecht jaar kan ik uitkomen op min 29% | E49: 0 | F49: =IF($E49="X",+$H49,0) -> 0 | H49: 3 | U49: 29 | V49: =CONCATENATE(Y49,Z49) -> 60RD40RM Neutrale offensiefe belegger | Y49: 60RD40RM | Z49: Neutrale offensiefe belegger
B50: 6 | C50: B | D50: Een gemiddeld rendement van 3%, maar in een slecht jaar kan ik uitkomen op min 14% | E50: X | F50: =IF($E50="X",+$H50,0) -> 2 | H50: 2 | U50: 30 | V50: =CONCATENATE(Y50,Z50) -> 60RD40RM Neutrale offensiefe belegger | Y50: 60RD40RM | Z50: Neutrale offensiefe belegger
B51: 6 | C51: C | D51: Een gemiddeld rendement van 1%, maar in een slecht jaar kan ik uitkomen op min 8% | E51: 0 | F51: =IF($E51="X",+$H51,0) -> 0 | H51: 1 | U51: 31 | V51: =CONCATENATE(Y51,Z51) -> 60RD40RM Neutrale offensiefe belegger | W51: 6 | Y51: 60RD40RM | Z51: Neutrale offensiefe belegger
B52: 6 | C52: D | D52: Een jaarlijks rendement gelijk aan de spaarrente, ook in een slecht jaar. | E52: 0 | F52: =IF($E52="X",+$H52,0) -> 0 | H52: 0 | U52: 32 | V52: =CONCATENATE(Y52,Z52) -> 60RD40RM Neutrale offensiefe belegger | Y52: 60RD40RM | Z52: Neutrale offensiefe belegger
B54: 7 | D54: Hoe vaak controleert u de waarde van uw portefeuille ? | U54: 33 | V54: =CONCATENATE(Y54,Z54) -> 70RD30RM Gematigd Offensieve belegger | Y54: 70RD30RM | Z54: Gematigd Offensieve belegger
B55: 7
B56: 7 | C56: A | D56: Iedere dag | E56: 0 | F56: =IF($E56="X",+$H56,0) -> 0 | H56: 0 | U56: 34 | V56: =CONCATENATE(Y56,Z56) -> 70RD30RM Gematigd Offensieve belegger | Y56: 70RD30RM | Z56: Gematigd Offensieve belegger
B57: 7 | C57: B | D57: Iedere maand | E57: 0 | F57: =IF($E57="X",+$H57,0) -> 0 | H57: 1 | U57: 35 | V57: =CONCATENATE(Y57,Z57) -> 70RD30RM Gematigd Offensieve belegger | Y57: 70RD30RM | Z57: Gematigd Offensieve belegger
B58: 7 | C58: C | D58: Ieder kwartaal | E58: X | F58: =IF($E58="X",+$H58,0) -> 2 | H58: 2 | U58: 36 | V58: =CONCATENATE(Y58,Z58) -> 70RD30RM Gematigd Offensieve belegger | W58: 4 | Y58: 70RD30RM | Z58: Gematigd Offensieve belegger
B59: 7 | C59: D | D59: Eens in het jaar | E59: 0 | F59: =IF($E59="X",+$H59,0) -> 0 | H59: 3 | U59: 37 | V59: =CONCATENATE(Y59,Z59) -> 80RD20RM Offensieve belegger | Y59: 80RD20RM | Z59: Offensieve belegger
B61: 8 | D61: Bij welke tussentijdse waardedaling van uw portefeuille maakt u zich nog geen zorgen ? | U61: 38 | V61: =CONCATENATE(Y61,Z61) -> 80RD20RM Offensieve belegger | Y61: 80RD20RM | Z61: Offensieve belegger
B63: 8 | C63: A | D63: Bij geen enkele, de waarde mag absoluut niet dalen | E63: X | F63: =IF($E63="X",+$H63,0) -> 0 | H63: 0 | U63: 39 | V63: =CONCATENATE(Y63,Z63) -> 80RD20RM Offensieve belegger | Y63: 80RD20RM | Z63: Offensieve belegger
B64: 8 | C64: B | D64: Bij een waardedaling kleiner dan 10% | E64: 0 | F64: =IF($E64="X",+$H64,0) -> 0 | H64: 1 | U64: 40 | V64: =CONCATENATE(Y64,Z64) -> 80RD20RM Offensieve belegger | Y64: 80RD20RM | Z64: Offensieve belegger
B65: 8 | C65: C | D65: Bij een waardedaling kleiner dan 25% | E65: 0 | F65: =IF($E65="X",+$H65,0) -> 0 | H65: 2 | U65: 41 | V65: =CONCATENATE(Y65,Z65) -> 80RD20RM Offensieve belegger | W65: 6 | Y65: 80RD20RM | Z65: Offensieve belegger
B66: 8 | C66: D | D66: Dat hangt af van het negatieve rendement van de markt (index) | E66: 0 | F66: =IF($E66="X",+$H66,0) -> 0 | H66: 3 | U66: 42 | V66: =CONCATENATE(Y66,Z66) -> 80RD20RM Offensieve belegger | Y66: 80RD20RM | Z66: Offensieve belegger
B68: 9 | D68: Waaruit bestaat uw huidige beleggingsportefeuille ? | U68: 43 | V68: =CONCATENATE(Y68,Z68) -> 100RD zeer offensieve belegger | Y68: 100RD | Z68: zeer offensieve belegger
B70: 9 | C70: A | D70: Geheel of bijna geheel uit cash en spaargeld | E70: 0 | F70: =IF($E70="X",+$H70,0) -> 0 | H70: 0 | U70: 44 | V70: =CONCATENATE(Y70,Z70) -> 100RD zeer offensieve belegger | W70: 3 | Y70: 100RD | Z70: zeer offensieve belegger
B71: 9 | C71: B | D71: Geheel of bijna geheel uit aandelen en/of derivaten | E71: 0 | F71: =IF($E71="X",+$H71,0) -> 0 | H71: 3 | U71: 45 | V71: =CONCATENATE(Y71,Z71) -> 100RD zeer offensieve belegger | Y71: 100RD | Z71: zeer offensieve belegger
B72: 9 | C72: C | D72: Een mengeling van aandelen, obligaties en andere beleggingen | E72: 0 | F72: =IF($E72="X",+$H72,0) -> 0 | H72: 2
B73: 9 | C73: D | D73: Geheel of bijna geheel uit obligaties en spaargeld | E73: X | F73: =IF($E73="X",+$H73,0) -> 1 | H73: 1 | U73: X
B75: 10 | D75: Wat is uw beleggershorizon ? (Hoelang denkt u uw beleggingen aan te houden?) | U75: 0
B77: 10 | C77: A | D77: Korter dan 1 jaar | E77: 0 | F77: =IF($E77="X",+$H77,0) -> 0 | H77: 0 | V77: TOTAAL | W77: =SUM(W8:W70) -> 46 | Z77: TOTAAL
B78: 10 | C78: B | D78: Langer dan 1 jaar, korter dan 5 jaar | E78: 0 | F78: =IF($E78="X",+$H78,0) -> 0 | H78: 0
B79: 10 | C79: C | D79: Langer dan 5 jaar, maar korter dan 10 jaar | E79: 0 | F79: =IF($E79="X",+$H79,0) -> 0 | H79: 2
B80: 10 | C80: D | D80: Langer dan 10 jaar, maar korter dan 15 jaar | E80: X | F80: =IF($E80="X",+$H80,0) -> 4 | H80: 4
B81: 10 | C81: E | D81: Langer dan 15 jaar | E81: 0 | F81: =IF($E81="X",+$H81,0) -> 0 | H81: 6
B83: 11 | D83: Heeft u ervaring met beleggen ?
B85: 11 | C85: A | D85: Ja, ruimschoots en voor langere tijd | E85: 0 | F85: =IF($E85="X",+$H85,0) -> 0 | H85: 6
B86: 11 | C86: B | D86: Ja, maar in beperkte mate | E86: 0 | F86: =IF($E86="X",+$H86,0) -> 0 | H86: 4
B87: 11 | C87: C | D87: Nee, maar ik volg wel het financiële nieuws | E87: X | F87: =IF($E87="X",+$H87,0) -> 2 | H87: 2
B88: 11 | C88: D | D88: Nee | E88: 0 | F88: =IF($E88="X",+$H88,0) -> 0 | H88: 0
D91: Dit is een controlevraag.Uw antwoord dient te passen bij uw risicoprofiel.
B93: 12 | D93: Wat is uw rendementsdoelstelling ?
C95: A | D95: 1% gemiddeld per jaar | E95: 0
C96: B | D96: 2% gemiddeld per jaar | E96: 0
C97: C | D97: 3% gemiddeld per jaar | E97: 0
C98: D | D98: 4% gemiddeld per jaar | E98: 0
C99: E | D99: 5% of meer | E99: x
D101: Risico-acceptatieprofiel op basis van de puntentelling :
D102: =VLOOKUP(E102,'Risicoprofiel bepalen - bron'!U8:V71,2,TRUE) -> 50RD50RM Neutrale belegger | E102: =SUM(F8:F99) -> 19
D103: Beleggingsprofiel
D105: 100RM => Zeer defensief : | E105: Punten: 0 - 2
D107: 20RD80RM => Defensief : | E107: Punten: 3 - 8
D109: 30RD70RM => Gematigd defensief : | E109: Punten: 9 - 12
D111: 40RD60RM => Neutraal defensief : | E111: Punten: 13 - 18
D113: 50RD50RM => Neutraal : | E113: Punten: 19 - 26
D115: 60RD40RM => Neutraal offensief : | E115: Punten: 27- 32
D117: 70RD30RM => Gematigd offensief : | E117: Punten: 33 - 36
D119: 80RD20RM => Offensief : | E119: Punten: 37 - 42
D121: 100RD => Zeer Offensief : | E121: Punten: 43-45

Sheet vragen org
A1: nummer | B1: vraag | C1: onderwerp | D1: antwoord_aanhef
A2: 1 | B2: Wat is uw beleggingsdoelstelling? | C2: beleggingsdoelstelling | D2: Mijn beleggingsdoelstelling is:
A3: 2 | B3: Bent U van plan tussentijds vermogen aan uw beleggingsportefeuille te onttrekken of juist vervolgstortingen te doen? | C3: bijstortingen | D3: Ik ben van plan:
A4: 3 | B4: Welke gevolgen heeft het niet halen van uw beleggingsdoelstellingen? | C4: gevolgen | D4: Het niet halen van doelstellingen:
A5: 4 | B5: Welk deel van uw vrij beschikbare vermogen (exclusief de eigen woning) is of wordt belegd op de rekening die wordt beheerd door B.A. van Doorn Comp? | C5: deel | D5: Het deel van mijn vermogen dat wordt beheerd door B.A. van Doorn Comp is:
A6: 5 | B6: Uw huidige inkomen (uit loon, pensioen onderneming ed) is : | C6: inkomen | D6: Mijn huidige inkomen is:
A7: 6 | B7: Welke kansverdeling spreekt u het meest aan voor het door U te beleggen vermogen? | C7: kansverdeling | D7: De volgende kansverdeling spreekt mij aan:
A8: 7 | B8: Hoe vaak controleert u de waarde van uw portefeuille? | C8: hoe_vaak | D8: Ik controleer de waarde van mijn beleggingen:
A9: 8 | B9: Bij welke tussentijdse waardedaling van uw portefeuille maakt u zich zorgen? | C9: waardedaling | D9: Ik maak me zorgen:
A10: 9 | B10: Waaruit bestaat uw huidige beleggingsportefeuille? | C10: huidige | D10: Mijn huidige beleggingen zijn:
A11: 10 | B11: Wat is uw beleggingshorizon? (Hoelang denkt u uw beleggingen aan te houden?) | C11: horizon | D11: Mijn beleggingshorizon is:
A12: 11 | B12: Heeft u ervaring met beleggen? | C12: ervaring | D12: Ervaring met beleggen:
A13: 12 | B13: Wat is uw rendementsdoelstelling? | C13: rendementsdoelstelling | D13: Mijn rendementsdoelstelling is:

Sheet vragen_antwoorden org
A1: nummer | B1: vraag | C1: onderwerp | D1: letter | E1: antwoord_aanhef | F1: antwoord | G1: punten | H1: selected
A2: 1 | B2: =VLOOKUP(A2,'vragen org'!A:B,2,0) -> Wat is uw beleggingsdoelstelling? | C2: =VLOOKUP(A2,'vragen org'!A:C,3,0) -> beleggingsdoelstelling | D2: A | E2: =VLOOKUP(A2,'vragen org'!A:E,4,0) -> Mijn beleggingsdoelstelling is: | F2: Vermogensgroei of vermogensbehoud met een bepaald doelvermogen | G2: 2
A3: 1 | B3: =VLOOKUP(A3,'vragen org'!A:B,2,0) -> Wat is uw beleggingsdoelstelling? | C3: =VLOOKUP(A3,'vragen org'!A:C,3,0) -> beleggingsdoelstelling | D3: B | E3: =VLOOKUP(A3,'vragen org'!A:E,4,0) -> Mijn beleggingsdoelstelling is: | F3: Vermogensgroei of vermogensbehoud zonder een bepaald doelvermogen | G3: 3 | H3: =F3 -> Vermogensgroei of vermogensbehoud zonder een bepaald doelvermogen
A4: 1 | B4: =VLOOKUP(A4,'vragen org'!A:B,2,0) -> Wat is uw beleggingsdoelstelling? | C4: =VLOOKUP(A4,'vragen org'!A:C,3,0) -> beleggingsdoelstelling | D4: C | E4: =VLOOKUP(A4,'vragen org'!A:E,4,0) -> Mijn beleggingsdoelstelling is: | F4: Een jaarlijkse aanvulling op het huidige inkomen | G4: 0
A5: 1 | B5: =VLOOKUP(A5,'vragen org'!A:B,2,0) -> Wat is uw beleggingsdoelstelling? | C5: =VLOOKUP(A5,'vragen org'!A:C,3,0) -> beleggingsdoelstelling | D5: D | E5: =VLOOKUP(A5,'vragen org'!A:E,4,0) -> Mijn beleggingsdoelstelling is: | F5: De financiering van een toekomstige uitgave, bv de studie van kinderen, of eerder stoppen met werken | G5: 1
A6: 2 | B6: =VLOOKUP(A6,'vragen org'!A:B,2,0) -> Bent U van plan tussentijds vermogen aan uw beleggingsportefeuille te onttrekken of juist vervolgstortingen te doen? | C6: =VLOOKUP(A6,'vragen org'!A:C,3,0) -> bijstortingen | D6: A | E6: =VLOOKUP(A6,'vragen org'!A:E,4,0) -> Ik ben van plan: | F6: Periodiek te onttrekken | G6: 0
A7: 2 | B7: =VLOOKUP(A7,'vragen org'!A:B,2,0) -> Bent U van plan tussentijds vermogen aan uw beleggingsportefeuille te onttrekken of juist vervolgstortingen te doen? | C7: =VLOOKUP(A7,'vragen org'!A:C,3,0) -> bijstortingen | D7: B | E7: =VLOOKUP(A7,'vragen org'!A:E,4,0) -> Ik ben van plan: | F7: Periodiek bij te storten | G7: 6
A8: 2 | B8: =VLOOKUP(A8,'vragen org'!A:B,2,0) -> Bent U van plan tussentijds vermogen aan uw beleggingsportefeuille te onttrekken of juist vervolgstortingen te doen? | C8: =VLOOKUP(A8,'vragen org'!A:C,3,0) -> bijstortingen | D8: C | E8: =VLOOKUP(A8,'vragen org'!A:E,4,0) -> Ik ben van plan: | F8: Incidenteel te onttrekken | G8: 2
A9: 2 | B9: =VLOOKUP(A9,'vragen org'!A:B,2,0) -> Bent U van plan tussentijds vermogen aan uw beleggingsportefeuille te onttrekken of juist vervolgstortingen te doen? | C9: =VLOOKUP(A9,'vragen org'!A:C,3,0) -> bijstortingen | D9: D | E9: =VLOOKUP(A9,'vragen org'!A:E,4,0) -> Ik ben van plan: | F9: Incidenteel bij te storten | G9: 4
A10: 2 | B10: =VLOOKUP(A10,'vragen org'!A:B,2,0) -> Bent U van plan tussentijds vermogen aan uw beleggingsportefeuille te onttrekken of juist vervolgstortingen te doen? | C10: =VLOOKUP(A10,'vragen org'!A:C,3,0) -> bijstortingen | D10: E | E10: =VLOOKUP(A10,'vragen org'!A:E,4,0) -> Ik ben van plan: | F10: Per saldo geen bijstortingen of onttrekkingen te doen | G10: 3 | H10: =F10 -> Per saldo geen bijstortingen of onttrekkingen te doen
A11: 3 | B11: =VLOOKUP(A11,'vragen org'!A:B,2,0) -> Welke gevolgen heeft het niet halen van uw beleggingsdoelstellingen? | C11: =VLOOKUP(A11,'vragen org'!A:C,3,0) -> gevolgen | D11: A | E11: =VLOOKUP(A11,'vragen org'!A:E,4,0) -> Het niet halen van doelstellingen: | F11: Heeft noch financiële, noch emotionele gevolgen | G11: 3
A12: 3 | B12: =VLOOKUP(A12,'vragen org'!A:B,2,0) -> Welke gevolgen heeft het niet halen van uw beleggingsdoelstellingen? | C12: =VLOOKUP(A12,'vragen org'!A:C,3,0) -> gevolgen | D12: B | E12: =VLOOKUP(A12,'vragen org'!A:E,4,0) -> Het niet halen van doelstellingen: | F12: Zou grote financiële en emotionele consequenties hebben | G12: 0
A13: 3 | B13: =VLOOKUP(A13,'vragen org'!A:B,2,0) -> Welke gevolgen heeft het niet halen van uw beleggingsdoelstellingen? | C13: =VLOOKUP(A13,'vragen org'!A:C,3,0) -> gevolgen | D13: C | E13: =VLOOKUP(A13,'vragen org'!A:E,4,0) -> Het niet halen van doelstellingen: | F13: Zou teleurstellend zijn, maar nauwelijks invloed hebben op mijn levenspeil | G13: 2 | H13: =F13 -> Zou teleurstellend zijn, maar nauwelijks invloed hebben op mijn levenspeil
A14: 3 | B14: =VLOOKUP(A14,'vragen org'!A:B,2,0) -> Welke gevolgen heeft het niet halen van uw beleggingsdoelstellingen? | C14: =VLOOKUP(A14,'vragen org'!A:C,3,0) -> gevolgen | D14: D | E14: =VLOOKUP(A14,'vragen org'!A:E,4,0) -> Het niet halen van doelstellingen: | F14: Zou leiden tot aanpassing van mijn levensstandaard | G14: 1
A15: 3 | B15: =VLOOKUP(A15,'vragen org'!A:B,2,0) -> Welke gevolgen heeft het niet halen van uw beleggingsdoelstellingen? | C15: =VLOOKUP(A15,'vragen org'!A:C,3,0) -> gevolgen | D15: E | E15: =VLOOKUP(A15,'vragen org'!A:E,4,0) -> Het niet halen van doelstellingen: | F15: Dit zou gevolgen hebben voor………………………. | G15: 1
A16: 4 | B16: =VLOOKUP(A16,'vragen org'!A:B,2,0) -> Welk deel van uw vrij beschikbare vermogen (exclusief de eigen woning) is of wordt belegd op de rekening die wordt beheerd door B.A. van Doorn Comp? | C16: =VLOOKUP(A16,'vragen org'!A:C,3,0) -> deel | D16: A | E16: =VLOOKUP(A16,'vragen org'!A:E,4,0) -> Het deel van mijn vermogen dat wordt beheerd door B.A. van Doorn Comp is: | F16: Meer dan 75% | G16: 0
A17: 4 | B17: =VLOOKUP(A17,'vragen org'!A:B,2,0) -> Welk deel van uw vrij beschikbare vermogen (exclusief de eigen woning) is of wordt belegd op de rekening die wordt beheerd door B.A. van Doorn Comp? | C17: =VLOOKUP(A17,'vragen org'!A:C,3,0) -> deel | D17: B | E17: =VLOOKUP(A17,'vragen org'!A:E,4,0) -> Het deel van mijn vermogen dat wordt beheerd door B.A. van Doorn Comp is: | F17: 50% - 75% | G17: 1
A18: 4 | B18: =VLOOKUP(A18,'vragen org'!A:B,2,0) -> Welk deel van uw vrij beschikbare vermogen (exclusief de eigen woning) is of wordt belegd op de rekening die wordt beheerd door B.A. van Doorn Comp? | C18: =VLOOKUP(A18,'vragen org'!A:C,3,0) -> deel | D18: C | E18: =VLOOKUP(A18,'vragen org'!A:E,4,0) -> Het deel van mijn vermogen dat wordt beheerd door B.A. van Doorn Comp is: | F18: 25% - 50% | G18: 2 | H18: =F18 -> 25% - 50%
A19: 4 | B19: =VLOOKUP(A19,'vragen org'!A:B,2,0) -> Welk deel van uw vrij beschikbare vermogen (exclusief de eigen woning) is of wordt belegd op de rekening die wordt beheerd door B.A. van Doorn Comp? | C19: =VLOOKUP(A19,'vragen org'!A:C,3,0) -> deel | D19: D | E19: =VLOOKUP(A19,'vragen org'!A:E,4,0) -> Het deel van mijn vermogen dat wordt beheerd door B.A. van Doorn Comp is: | F19: Minder dan 25% | G19: 3
A20: 5 | B20: =VLOOKUP(A20,'vragen org'!A:B,2,0) -> Uw huidige inkomen (uit loon, pensioen onderneming ed) is : | C20: =VLOOKUP(A20,'vragen org'!A:C,3,0) -> inkomen | D20: A | E20: =VLOOKUP(A20,'vragen org'!A:E,4,0) -> Mijn huidige inkomen is: | F20: Onvoldoende om uw vaste lasten en kosten van levensonderhoud te betalen. | G20: 0
A21: 5 | B21: =VLOOKUP(A21,'vragen org'!A:B,2,0) -> Uw huidige inkomen (uit loon, pensioen onderneming ed) is : | C21: =VLOOKUP(A21,'vragen org'!A:C,3,0) -> inkomen | D21: B | E21: =VLOOKUP(A21,'vragen org'!A:E,4,0) -> Mijn huidige inkomen is: | F21: Soms voldoende, soms onvoldoende. Aan het eind van het jaar komt u ongeveer uit. | G21: 2
A22: 5 | B22: =VLOOKUP(A22,'vragen org'!A:B,2,0) -> Uw huidige inkomen (uit loon, pensioen onderneming ed) is : | C22: =VLOOKUP(A22,'vragen org'!A:C,3,0) -> inkomen | D22: C | E22: =VLOOKUP(A22,'vragen org'!A:E,4,0) -> Mijn huidige inkomen is: | F22: Voldoende om uw vaste lasten en kosten van levensonderhoud te betalen. | G22: 4 | H22: =F22 -> Voldoende om uw vaste lasten en kosten van levensonderhoud te betalen.
A23: 5 | B23: =VLOOKUP(A23,'vragen org'!A:B,2,0) -> Uw huidige inkomen (uit loon, pensioen onderneming ed) is : | C23: =VLOOKUP(A23,'vragen org'!A:C,3,0) -> inkomen | D23: D | E23: =VLOOKUP(A23,'vragen org'!A:E,4,0) -> Mijn huidige inkomen is: | F23: Ruim voldoende om uw vaste lasten en kosten van levensonderhoud te betalen. | G23: 6
A24: 5 | B24: =VLOOKUP(A24,'vragen org'!A:B,2,0) -> Uw huidige inkomen (uit loon, pensioen onderneming ed) is : | C24: =VLOOKUP(A24,'vragen org'!A:C,3,0) -> inkomen | D24: E | E24: =VLOOKUP(A24,'vragen org'!A:E,4,0) -> Mijn huidige inkomen is: | F24: Voldoende om maandelijks een aanzienlijk bedrag opzij te zetten. | G24: 8
A25: 6 | B25: =VLOOKUP(A25,'vragen org'!A:B,2,0) -> Welke kansverdeling spreekt u het meest aan voor het door U te beleggen vermogen? | C25: =VLOOKUP(A25,'vragen org'!A:C,3,0) -> kansverdeling | D25: A | E25: =VLOOKUP(A25,'vragen org'!A:E,4,0) -> De volgende kansverdeling spreekt mij aan: | F25: Een gemiddeld rendement van 6%, maar in een slecht jaar kan ik uitkomen op min 29% | G25: 3
A26: 6 | B26: =VLOOKUP(A26,'vragen org'!A:B,2,0) -> Welke kansverdeling spreekt u het meest aan voor het door U te beleggen vermogen? | C26: =VLOOKUP(A26,'vragen org'!A:C,3,0) -> kansverdeling | D26: B | E26: =VLOOKUP(A26,'vragen org'!A:E,4,0) -> De volgende kansverdeling spreekt mij aan: | F26: Een gemiddeld rendement van 3%, maar in een slecht jaar kan ik uitkomen op min 14% | G26: 2 | H26: =F26 -> Een gemiddeld rendement van 3%, maar in een slecht jaar kan ik uitkomen op min 14%
A27: 6 | B27: =VLOOKUP(A27,'vragen org'!A:B,2,0) -> Welke kansverdeling spreekt u het meest aan voor het door U te beleggen vermogen? | C27: =VLOOKUP(A27,'vragen org'!A:C,3,0) -> kansverdeling | D27: C | E27: =VLOOKUP(A27,'vragen org'!A:E,4,0) -> De volgende kansverdeling spreekt mij aan: | F27: Een gemiddeld rendement van 1%, maar in een slecht jaar kan ik uitkomen op min 8% | G27: 1
A28: 6 | B28: =VLOOKUP(A28,'vragen org'!A:B,2,0) -> Welke kansverdeling spreekt u het meest aan voor het door U te beleggen vermogen? | C28: =VLOOKUP(A28,'vragen org'!A:C,3,0) -> kansverdeling | D28: D | E28: =VLOOKUP(A28,'vragen org'!A:E,4,0) -> De volgende kansverdeling spreekt mij aan: | F28: Een jaarlijks rendement gelijk aan de spaarrente, ook in een slecht jaar. | G28: 0
A29: 7 | B29: =VLOOKUP(A29,'vragen org'!A:B,2,0) -> Hoe vaak controleert u de waarde van uw portefeuille? | C29: =VLOOKUP(A29,'vragen org'!A:C,3,0) -> hoe_vaak | D29: A | E29: =VLOOKUP(A29,'vragen org'!A:E,4,0) -> Ik controleer de waarde van mijn beleggingen: | F29: Iedere dag | G29: 0
A30: 7 | B30: =VLOOKUP(A30,'vragen org'!A:B,2,0) -> Hoe vaak controleert u de waarde van uw portefeuille? | C30: =VLOOKUP(A30,'vragen org'!A:C,3,0) -> hoe_vaak | D30: B | E30: =VLOOKUP(A30,'vragen org'!A:E,4,0) -> Ik controleer de waarde van mijn beleggingen: | F30: Iedere maand | G30: 1
A31: 7 | B31: =VLOOKUP(A31,'vragen org'!A:B,2,0) -> Hoe vaak controleert u de waarde van uw portefeuille? | C31: =VLOOKUP(A31,'vragen org'!A:C,3,0) -> hoe_vaak | D31: C | E31: =VLOOKUP(A31,'vragen org'!A:E,4,0) -> Ik controleer de waarde van mijn beleggingen: | F31: Ieder kwartaal | G31: 2 | H31: =F31 -> Ieder kwartaal
A32: 7 | B32: =VLOOKUP(A32,'vragen org'!A:B,2,0) -> Hoe vaak controleert u de waarde van uw portefeuille? | C32: =VLOOKUP(A32,'vragen org'!A:C,3,0) -> hoe_vaak | D32: D | E32: =VLOOKUP(A32,'vragen org'!A:E,4,0) -> Ik controleer de waarde van mijn beleggingen: | F32: Eens in het jaar | G32: 3
A33: 8 | B33: =VLOOKUP(A33,'vragen org'!A:B,2,0) -> Bij welke tussentijdse waardedaling van uw portefeuille maakt u zich zorgen? | C33: =VLOOKUP(A33,'vragen org'!A:C,3,0) -> waardedaling | D33: A | E33: =VLOOKUP(A33,'vragen org'!A:E,4,0) -> Ik maak me zorgen: | F33: Bij elke waardedaling, de waarde mag absoluut niet dalen | G33: 0
A34: 8 | B34: =VLOOKUP(A34,'vragen org'!A:B,2,0) -> Bij welke tussentijdse waardedaling van uw portefeuille maakt u zich zorgen? | C34: =VLOOKUP(A34,'vragen org'!A:C,3,0) -> waardedaling | D34: B | E34: =VLOOKUP(A34,'vragen org'!A:E,4,0) -> Ik maak me zorgen: | F34: Bij een waardedaling groter dan 10% | G34: 1
A35: 8 | B35: =VLOOKUP(A35,'vragen org'!A:B,2,0) -> Bij welke tussentijdse waardedaling van uw portefeuille maakt u zich zorgen? | C35: =VLOOKUP(A35,'vragen org'!A:C,3,0) -> waardedaling | D35: C | E35: =VLOOKUP(A35,'vragen org'!A:E,4,0) -> Ik maak me zorgen: | F35: Bij een waardedaling groter dan 25% | G35: 2 | H35: =F35 -> Bij een waardedaling groter dan 25%
A36: 8 | B36: =VLOOKUP(A36,'vragen org'!A:B,2,0) -> Bij welke tussentijdse waardedaling van uw portefeuille maakt u zich zorgen? | C36: =VLOOKUP(A36,'vragen org'!A:C,3,0) -> waardedaling | D36: D | E36: =VLOOKUP(A36,'vragen org'!A:E,4,0) -> Ik maak me zorgen: | F36: Dit hangt af van het negatieve rendement van de markt (index) | G36: 3
A37: 9 | B37: =VLOOKUP(A37,'vragen org'!A:B,2,0) -> Waaruit bestaat uw huidige beleggingsportefeuille? | C37: =VLOOKUP(A37,'vragen org'!A:C,3,0) -> huidige | D37: A | E37: =VLOOKUP(A37,'vragen org'!A:E,4,0) -> Mijn huidige beleggingen zijn: | F37: Alleen of nagenoeg alleen cash en spaargeld | G37: 0
A38: 9 | B38: =VLOOKUP(A38,'vragen org'!A:B,2,0) -> Waaruit bestaat uw huidige beleggingsportefeuille? | C38: =VLOOKUP(A38,'vragen org'!A:C,3,0) -> huidige | D38: B | E38: =VLOOKUP(A38,'vragen org'!A:E,4,0) -> Mijn huidige beleggingen zijn: | F38: Alleen of bijna alleen aandelen en/of derivaten | G38: 3
A39: 9 | B39: =VLOOKUP(A39,'vragen org'!A:B,2,0) -> Waaruit bestaat uw huidige beleggingsportefeuille? | C39: =VLOOKUP(A39,'vragen org'!A:C,3,0) -> huidige | D39: C | E39: =VLOOKUP(A39,'vragen org'!A:E,4,0) -> Mijn huidige beleggingen zijn: | F39: Een mengeling van aandelen, obligaties en andere beleggingen | G39: 2 | H39: =F39 -> Een mengeling van aandelen, obligaties en andere beleggingen
A40: 9 | B40: =VLOOKUP(A40,'vragen org'!A:B,2,0) -> Waaruit bestaat uw huidige beleggingsportefeuille? | C40: =VLOOKUP(A40,'vragen org'!A:C,3,0) -> huidige | D40: D | E40: =VLOOKUP(A40,'vragen org'!A:E,4,0) -> Mijn huidige beleggingen zijn: | F40: Alleen of bijna alleen obligaties en spaargeld | G40: 1
A41: 10 | B41: =VLOOKUP(A41,'vragen org'!A:B,2,0) -> Wat is uw beleggingshorizon? (Hoelang denkt u uw beleggingen aan te houden?) | C41: =VLOOKUP(A41,'vragen org'!A:C,3,0) -> horizon | D41: A | E41: =VLOOKUP(A41,'vragen org'!A:E,4,0) -> Mijn beleggingshorizon is: | F41: Ongeveer 1 jaar | G41: 0
A42: 10 | B42: =VLOOKUP(A42,'vragen org'!A:B,2,0) -> Wat is uw beleggingshorizon? (Hoelang denkt u uw beleggingen aan te houden?) | C42: =VLOOKUP(A42,'vragen org'!A:C,3,0) -> horizon | D42: B | E42: =VLOOKUP(A42,'vragen org'!A:E,4,0) -> Mijn beleggingshorizon is: | F42: Ongeveer 3 jaar | G42: 0
A43: 10 | B43: =VLOOKUP(A43,'vragen org'!A:B,2,0) -> Wat is uw beleggingshorizon? (Hoelang denkt u uw beleggingen aan te houden?) | C43: =VLOOKUP(A43,'vragen org'!A:C,3,0) -> horizon | D43: C | E43: =VLOOKUP(A43,'vragen org'!A:E,4,0) -> Mijn beleggingshorizon is: | F43: Ongeveer 5 jaar | G43: 2
A44: 10 | B44: =VLOOKUP(A44,'vragen org'!A:B,2,0) -> Wat is uw beleggingshorizon? (Hoelang denkt u uw beleggingen aan te houden?) | C44: =VLOOKUP(A44,'vragen org'!A:C,3,0) -> horizon | D44: D | E44: =VLOOKUP(A44,'vragen org'!A:E,4,0) -> Mijn beleggingshorizon is: | F44: Ongeveer 10 jaar | G44: 4 | H44: =F44 -> Ongeveer 10 jaar
A45: 10 | B45: =VLOOKUP(A45,'vragen org'!A:B,2,0) -> Wat is uw beleggingshorizon? (Hoelang denkt u uw beleggingen aan te houden?) | C45: =VLOOKUP(A45,'vragen org'!A:C,3,0) -> horizon | D45: E | E45: =VLOOKUP(A45,'vragen org'!A:E,4,0) -> Mijn beleggingshorizon is: | F45: Misschien wel 30 jaar | G45: 6
A46: 11 | B46: =VLOOKUP(A46,'vragen org'!A:B,2,0) -> Heeft u ervaring met beleggen? | C46: =VLOOKUP(A46,'vragen org'!A:C,3,0) -> ervaring | D46: A | E46: =VLOOKUP(A46,'vragen org'!A:E,4,0) -> Ervaring met beleggen: | F46: Ja, ruimschoots en voor langere tijd | G46: 6
A47: 11 | B47: =VLOOKUP(A47,'vragen org'!A:B,2,0) -> Heeft u ervaring met beleggen? | C47: =VLOOKUP(A47,'vragen org'!A:C,3,0) -> ervaring | D47: B | E47: =VLOOKUP(A47,'vragen org'!A:E,4,0) -> Ervaring met beleggen: | F47: Ja, maar in beperkte mate | G47: 4 | H47: =F47 -> Ja, maar in beperkte mate
A48: 11 | B48: =VLOOKUP(A48,'vragen org'!A:B,2,0) -> Heeft u ervaring met beleggen? | C48: =VLOOKUP(A48,'vragen org'!A:C,3,0) -> ervaring | D48: C | E48: =VLOOKUP(A48,'vragen org'!A:E,4,0) -> Ervaring met beleggen: | F48: Nee, maar ik volg wel het financiële nieuws | G48: 2
A49: 11 | B49: =VLOOKUP(A49,'vragen org'!A:B,2,0) -> Heeft u ervaring met beleggen? | C49: =VLOOKUP(A49,'vragen org'!A:C,3,0) -> ervaring | D49: D | E49: =VLOOKUP(A49,'vragen org'!A:E,4,0) -> Ervaring met beleggen: | F49: Nee | G49: 0
A50: 12 | B50: =VLOOKUP(A50,'vragen org'!A:B,2,0) -> Wat is uw rendementsdoelstelling? | C50: =VLOOKUP(A50,'vragen org'!A:C,3,0) -> rendementsdoelstelling | D50: A | E50: =VLOOKUP(A50,'vragen org'!A:E,4,0) -> Mijn rendementsdoelstelling is: | F50: 1% gemiddeld per jaar | G50: 0
A51: 12 | B51: =VLOOKUP(A51,'vragen org'!A:B,2,0) -> Wat is uw rendementsdoelstelling? | C51: =VLOOKUP(A51,'vragen org'!A:C,3,0) -> rendementsdoelstelling | D51: B | E51: =VLOOKUP(A51,'vragen org'!A:E,4,0) -> Mijn rendementsdoelstelling is: | F51: 2% gemiddeld per jaar | G51: 0
A52: 12 | B52: =VLOOKUP(A52,'vragen org'!A:B,2,0) -> Wat is uw rendementsdoelstelling? | C52: =VLOOKUP(A52,'vragen org'!A:C,3,0) -> rendementsdoelstelling | D52: C | E52: =VLOOKUP(A52,'vragen org'!A:E,4,0) -> Mijn rendementsdoelstelling is: | F52: 3% gemiddeld per jaar | G52: 0
A53: 12 | B53: =VLOOKUP(A53,'vragen org'!A:B,2,0) -> Wat is uw rendementsdoelstelling? | C53: =VLOOKUP(A53,'vragen org'!A:C,3,0) -> rendementsdoelstelling | D53: D | E53: =VLOOKUP(A53,'vragen org'!A:E,4,0) -> Mijn rendementsdoelstelling is: | F53: 4% gemiddeld per jaar | G53: 0 | H53: =F53 -> 4% gemiddeld per jaar
A54: 12 | B54: =VLOOKUP(A54,'vragen org'!A:B,2,0) -> Wat is uw rendementsdoelstelling? | C54: =VLOOKUP(A54,'vragen org'!A:C,3,0) -> rendementsdoelstelling | D54: E | E54: =VLOOKUP(A54,'vragen org'!A:E,4,0) -> Mijn rendementsdoelstelling is: | F54: 5% of meer | G54: 0

Sheet vragen_antwoorden_prive_nl
A1: categorie | B1: onderwerp | C1: vraag | D1: antwoord | E1: punten | F1: selected
A2: beleggingsdoelstelling | B2: beleggingsdoelstelling | C2: Ik wil mijn vermogen beleggen | D2: zodat ik hiermee binnen afzienbare tijd een uitgave kan betalen - zie ook de invulvelden hieronder | E2: 1
A3: beleggingsdoelstelling | B3: beleggingsdoelstelling | C3: Ik wil mijn vermogen beleggen | D3: om het grotendeels in stand te houden | E3: 2
A4: beleggingsdoelstelling | B4: beleggingsdoelstelling | C4: Ik wil mijn vermogen beleggen | D4: om het zonder veel neerwaarts risico te beleggen, met kans op enige groei. | E4: 3
A5: beleggingsdoelstelling | B5: beleggingsdoelstelling | C5: Ik wil mijn vermogen beleggen | D5: om het te laten groeien op de langere termijn | E5: 4 | F5: =D5 -> om het te laten groeien op de langere termijn
A6: beleggingsdoelstelling | B6: beleggingsdoelstelling | C6: Ik wil mijn vermogen beleggen | D6: om op de lange termijn kans te hebben op het hoogste resultaat | E6: 5
A7: beleggingsdoelstelling | B7: beleggingsdoelstelling_toelichting | C7: Wilt u een toelichting geven op uw beleggingsdoelstelling? | D7: nee, dat is in het antwoord op de vorige vraag voldoende verwoord | E7: 0 | F7: =D7 -> nee, dat is in het antwoord op de vorige vraag voldoende verwoord
A8: beleggingsdoelstelling | B8: beleggingsdoelstelling_toelichting | C8: Wilt u een toelichting geven op uw beleggingsdoelstelling? | D8: ja graag - hieronder opent een tekstvakje waarin u een toelichting kunt schrijven | E8: 0
A9: financiele_situatie | B9: eigen_vermogen_omvang | C9: Eigen vermogen is de waarde van uw bezittingen minus de schulden, zoals een hypotheek. Mijn eigen vermogen | D9: is niet voldoende om mijn bestedingspatroon te kunnen handhaven | E9: 1
A10: financiele_situatie | B10: eigen_vermogen_omvang | C10: Eigen vermogen is de waarde van uw bezittingen minus de schulden, zoals een hypotheek. Mijn eigen vermogen | D10: is voldoende om mijn bestedingspatroon te handhaven | E10: 2 | F10: =D10 -> is voldoende om mijn bestedingspatroon te handhaven
A11: financiele_situatie | B11: eigen_vermogen_omvang | C11: Eigen vermogen is de waarde van uw bezittingen minus de schulden, zoals een hypotheek. Mijn eigen vermogen | D11: overstijgt ruimschoots de behoefte aan reguliere uitgaven in de toekomst | E11: 3
A12: financiele_situatie | B12: eigen_vermogen_liquiditeit | C12: Het eigen vermogen kan vrij belegbaar zijn en/of belegd zijn in vastgoed of andere minder makkelijk verhandelbare vermogensbestanddelen. Mijn eigen vermogen | D12: is slechts beperkt vrij te beleggen en bestaat uit vastgoed (waaronder de eigen woning) en/of minder makkelijk verhandelbare vermogensbestanddelen | E12: 1
A13: financiele_situatie | B13: eigen_vermogen_liquiditeit | C13: Het eigen vermogen kan vrij belegbaar zijn en/of belegd zijn in vastgoed of andere minder makkelijk verhandelbare vermogensbestanddelen. Mijn eigen vermogen | D13: is grotendeels vrij te beleggen en bestaat deels uit vastgoed (waaronder de eigen woning) en/of minder makkelijk verhandelbare vermogensbestanddelen | E13: 2 | F13: =D13 -> is grotendeels vrij te beleggen en bestaat deels uit vastgoed (waaronder de eigen woning) en/of minder makkelijk verhandelbare vermogensbestanddelen
A14: financiele_situatie | B14: eigen_vermogen_liquiditeit | C14: Het eigen vermogen kan vrij belegbaar zijn en/of belegd zijn in vastgoed of andere minder makkelijk verhandelbare vermogensbestanddelen. Mijn eigen vermogen | D14: is vrij te beleggen | E14: 3
A15: financiele_situatie | B15: deel | C15: Het deel van het vrij belegbare vermogen dat ik bij B.A. van Doorn onderbreng | D15: is een kwart of minder | E15: 3
A16: financiele_situatie | B16: deel | C16: Het deel van het vrij belegbare vermogen dat ik bij B.A. van Doorn onderbreng | D16: is ongeveer de helft | E16: 2 | F16: =D16 -> is ongeveer de helft
A17: financiele_situatie | B17: deel | C17: Het deel van het vrij belegbare vermogen dat ik bij B.A. van Doorn onderbreng | D17: is meer dan de helft | E17: 1
A18: financiele_situatie | B18: inkomen | C18: Mijn inkomen (zoals uit loon, pensioen, of onderneming) | D18: is onvoldoende om van te leven en ik moet periodiek onttrekkingen doen | E18: 1
A19: financiele_situatie | B19: inkomen | C19: Mijn inkomen (zoals uit loon, pensioen, of onderneming) | D19: is genoeg om van te leven, waardoor ik slechts incidenteel onttrekkingen hoef te doen | E19: 2
A20: financiele_situatie | B20: inkomen | C20: Mijn inkomen (zoals uit loon, pensioen, of onderneming) | D20: is meer dan voldoende en ik kan mijn vermogen laten groeien, behoudens evt. onttrekkingen voor box3-belasting | E20: 3 | F20: =D20 -> is meer dan voldoende en ik kan mijn vermogen laten groeien, behoudens evt. onttrekkingen voor box3-belasting
A21: financiele_situatie | B21: gevolgen_materieel | C21: Louter financieel gezien, zonder mijn bestedingspatroon te hoeven bijstellen, | D21: kan ik maar een beperkte waardedaling van mijn beleggingen hebben | E21: 1
A22: financiele_situatie | B22: gevolgen_materieel | C22: Louter financieel gezien, zonder mijn bestedingspatroon te hoeven bijstellen, | D22: kan ik een waardedaling van mijn beleggingen aan van ongeveer 25% | E22: 2 | F22: =D22 -> kan ik een waardedaling van mijn beleggingen aan van ongeveer 25%
A23: financiele_situatie | B23: gevolgen_materieel | C23: Louter financieel gezien, zonder mijn bestedingspatroon te hoeven bijstellen, | D23: kan ik een waardedaling van mijn beleggingen aan van wel zo'n 40% | E23: 3
A24: financiele_situatie | B24: huidige_samenstelling | C24: Mijn huidige vrij belegbare vermogen (dus naast de eigen woning) | D24: bestaat overwegend uit spaargeld en/of obligaties | E24: 0
A25: financiele_situatie | B25: huidige_samenstelling | C25: Mijn huidige vrij belegbare vermogen (dus naast de eigen woning) | D25: is belegd in een portefeuille aandelen en obligaties | E25: 0 | F25: =D25 -> is belegd in een portefeuille aandelen en obligaties
A26: financiele_situatie | B26: huidige_samenstelling | C26: Mijn huidige vrij belegbare vermogen (dus naast de eigen woning) | D26: is vooral belegd in aandelen en andere risicodragende beleggingen | E26: 0
A27: kennis_ervaring | B27: kennis_beleggen | C27: Mijn kennis van beleggen | D27: is beperkt, ik weet er weinig van | E27: 1
A28: kennis_ervaring | B28: kennis_beleggen | C28: Mijn kennis van beleggen | D28: is gemiddeld en ik volg af en toe het financiële nieuws | E28: 2 | F28: =D28 -> is gemiddeld en ik volg af en toe het financiële nieuws
A29: kennis_ervaring | B29: kennis_beleggen | C29: Mijn kennis van beleggen | D29: is uitgebreid en ik volg het financiële nieuws op de voet | E29: 3
A30: kennis_ervaring | B30: kennis_instrumenten | C30: Mijn kennis van beleggingsinstrumenten | D30: is beperkt, ik weet er weinig van | E30: 1
A31: kennis_ervaring | B31: kennis_instrumenten | C31: Mijn kennis van beleggingsinstrumenten | D31: is aanwezig, ik weet wat aandelen en obligaties zijn | E31: 2 | F31: =D31 -> is aanwezig, ik weet wat aandelen en obligaties zijn
A32: kennis_ervaring | B32: kennis_instrumenten | C32: Mijn kennis van beleggingsinstrumenten | D32: is aanwezig, ik weet wat aandelen, obligaties en alternatieve beleggingen zijn | E32: 3
A33: kennis_ervaring | B33: ervaring_beleggingsdienstverlening | C33: Met beleggingsdienstverlening | D33: heb ik geen ervaring | E33: 1
A34: kennis_ervaring | B34: ervaring_beleggingsdienstverlening | C34: Met beleggingsdienstverlening | D34: heb ik ervaring, vooral met beleggingsadvies en/of execution only | E34: 3
A35: kennis_ervaring | B35: ervaring_beleggingsdienstverlening | C35: Met beleggingsdienstverlening | D35: heb ik ervaring, vooral met vermogensbeheer | E35: 2 | F35: =D35 -> heb ik ervaring, vooral met vermogensbeheer
A36: kennis_ervaring | B36: ervaring_beleggen | C36: Mijn ervaring met beleggen | D36: Ik heb geen ervaring met beleggen | E36: 1
A37: kennis_ervaring | B37: ervaring_beleggen | C37: Mijn ervaring met beleggen | D37: is beperkt | E37: 2
A38: kennis_ervaring | B38: ervaring_beleggen | C38: Mijn ervaring met beleggen | D38: is ruim aanwezig | E38: 3 | F38: =D38 -> is ruim aanwezig
A39: risicobereidheid | B39: gevolgen_emotioneel | C39: Als het gaat om slechte beleggingsresultaten | D39: daar kan ik, emotioneel gezien, niet goed tegen | E39: 1
A40: risicobereidheid | B40: gevolgen_emotioneel | C40: Als het gaat om slechte beleggingsresultaten | D40: ben ik bereid, op enig moment, ongeveer 25% waardedaling te accepteren | E40: 2 | F40: =D40 -> ben ik bereid, op enig moment, ongeveer 25% waardedaling te accepteren
A41: risicobereidheid | B41: gevolgen_emotioneel | C41: Als het gaat om slechte beleggingsresultaten | D41: ben ik bereid, op enig moment, ongeveer 40% waardedaling te accepteren | E41: 3
A42: risicobereidheid | B42: hoe_vaak | C42: De waarde van mijn beleggingen zal fluctueren. | D42: Ik check het geregeld en zit er bovenop | E42: 1 | F42: =D42 -> Ik check het geregeld en zit er bovenop
A43: risicobereidheid | B43: hoe_vaak | C43: De waarde van mijn beleggingen zal fluctueren. | D43: Ik wacht de kwartaalrapportage af | E43: 2
A44: risicobereidheid | B44: hoe_vaak | C44: De waarde van mijn beleggingen zal fluctueren. | D44: Ik kijk een keer per jaar en minder dan een keer per kwartaal | E44: 3
A45: risicobereidheid | B45: beleggingshorizon | C45: Wat betreft mijn beleggingshorizon is het volgende van toepassing: | D45: ik beleg voor een jaar of vijf | E45: 1
A46: risicobereidheid | B46: beleggingshorizon | C46: Wat betreft mijn beleggingshorizon is het volgende van toepassing: | D46: Ik kan mijn beleggingen wel tien jaar aanhouden en heb er geen tussentijdse plannen mee | E46: 2 | F46: =D46 -> Ik kan mijn beleggingen wel tien jaar aanhouden en heb er geen tussentijdse plannen mee
A47: risicobereidheid | B47: beleggingshorizon | C47: Wat betreft mijn beleggingshorizon is het volgende van toepassing: | D47: Ik beleg voor een periode langer dan tien jaar | E47: 3
A48: risicobereidheid | B48: doel_niet_halen | C48: Als ik mijn beleggingsdoelstelling niet haal | D48: Dat zou buitengewoon teleurstellend zijn | E48: 1
A49: risicobereidheid | B49: doel_niet_halen | C49: Als ik mijn beleggingsdoelstelling niet haal | D49: Dat zou teleurstellend zijn | E49: 2
A50: risicobereidheid | B50: doel_niet_halen | C50: Als ik mijn beleggingsdoelstelling niet haal | D50: Dat kan gebeuren, want beleggen gaat nu eenmaal gepaard met risico's | E50: 3 | F50: =D50 -> Dat kan gebeuren, want beleggen gaat nu eenmaal gepaard met risico's
A51: duurzaamheid | B51: duurzaamheid_nu | C51: In de samenstelling van mijn huidige beleggingsportefeuille | D51: speelt duurzaamheid geen rol want ik beleg nog niet | E51: 0
A52: duurzaamheid | B52: duurzaamheid_nu | C52: In de samenstelling van mijn huidige beleggingsportefeuille | D52: spelen duurzaamheidsaspecten geen bijzondere rol | E52: 0 | F52: =D52 -> spelen duurzaamheidsaspecten geen bijzondere rol
A53: duurzaamheid | B53: duurzaamheid_nu | C53: In de samenstelling van mijn huidige beleggingsportefeuille | D53: spelen duurzaamheidsaspecten een bijzondere rol | E53: 0
A54: duurzaamheid | B54: duurzaamheid_bavd | C54: Bij de samenstelling van mijn portefeuille bij B.A. van Doorn | D54: heb ik geen duurzaamheidsvoorkeuren | E54: 0 | F54: =D54 -> heb ik geen duurzaamheidsvoorkeuren
A55: duurzaamheid | B55: duurzaamheid_bavd | C55: Bij de samenstelling van mijn portefeuille bij B.A. van Doorn | D55: moet rekening gehouden worden met de belangrijkste nadelige effecten op duurzaamheidsfactoren zoals hierboven genoemd | E55: 0
A56: duurzaamheid | B56: duurzaamheid_percentage | C56: Wat betreft het gedeelte duurzame beleggingen in onze portefeuille | D56: wil ik dat dit meer is dan een kwart | E56: 0 | F56: =D56 -> wil ik dat dit meer is dan een kwart
A57: duurzaamheid | B57: duurzaamheid_percentage | C57: Wat betreft het gedeelte duurzame beleggingen in onze portefeuille | D57: wil ik dat dit meer is dan de helft | E57: 0
A58: duurzaamheid | B58: duurzaamheid_taxonomie | C58: Zogenaamde Europese Taxonomie-beleggingen | D58: zijn geen vereiste voor de invulling van onze portefeuille | E58: 0 | F58: =D58 -> zijn geen vereiste voor de invulling van onze portefeuille
A59: duurzaamheid | B59: duurzaamheid_taxonomie | C59: Zogenaamde Europese Taxonomie-beleggingen | D59: moeten meer dan 10% uitmaken van de portfeuille | E59: 0
A60: overig | B60: overig | C60: Wilt u een toelichting geven op overige zaken die niet aan de orde zijn gekomen? | D60: nee, dat is niet nodig | E60: 0 | F60: =D60 -> nee, dat is niet nodig
A61: overig | B61: overig | C61: Wilt u een toelichting geven op overige zaken die niet aan de orde zijn gekomen? | D61: ja graag - hieronder opent een tekstvakje waarin u een toelichting kunt schrijven | E61: 0
A62: private_beleggingen | B62: private_beleggingen | C62: Gegeven de genoemde mogelijke voor- en nadelen van private beleggingen | D62: stel ik prijs op het opnemen van private beleggingen in de portefeuille | E62: 0 | F62: stel ik prijs op het opnemen van private beleggingen in de portefeuille
A63: private_beleggingen | B63: private_beleggingen | C63: Gegeven de genoemde mogelijke voor- en nadelen van private beleggingen | D63: heb ik geen interesse in private beleggingen | E63: 0

Sheet vragen_antwoorden_prive_en
A1: categorie | B1: onderwerp | C1: vraag | D1: antwoord | E1: punten | F1: selected
A2: beleggingsdoelstelling | B2: beleggingsdoelstelling | C2: I want to invest my assets | D2: so that I can pay for an expense in the foreseeable future - see also the input fields below | E2: 1
A3: beleggingsdoelstelling | B3: beleggingsdoelstelling | C3: I want to invest my assets | D3: to preserve it for the most part | E3: 2
A4: beleggingsdoelstelling | B4: beleggingsdoelstelling | C4: I want to invest my assets | D4: to invest it without much downside risk, with the chance of some growth. | E4: 3
A5: beleggingsdoelstelling | B5: beleggingsdoelstelling | C5: I want to invest my assets | D5: to grow it in the longer term | E5: 4 | F5: to grow it in the longer term
A6: beleggingsdoelstelling | B6: beleggingsdoelstelling | C6: I want to invest my assets | D6: to have a chance of achieving the highest result in the long term | E6: 5
A7: beleggingsdoelstelling | B7: beleggingsdoelstelling_toelichting | C7: Would you like to explain your investment objective? | D7: No, that is sufficiently expressed in the answer to the previous question | E7: 0 | F7: No, that is sufficiently expressed in the answer to the previous question
A8: beleggingsdoelstelling | B8: beleggingsdoelstelling_toelichting | C8: Would you like to explain your investment objective? | D8: Yes please - below a text box opens in which you can write an explanation | E8: 0
A9: financiele_situatie | B9: eigen_vermogen_omvang | C9: Equity is the value of your assets minus debts, such as a mortgage. My equity | D9: is not enough to maintain my spending habits | E9: 1
A10: financiele_situatie | B10: eigen_vermogen_omvang | C10: Equity is the value of your assets minus debts, such as a mortgage. My equity | D10: is enough to maintain my spending habits | E10: 2 | F10: is enough to maintain my spending habits
A11: financiele_situatie | B11: eigen_vermogen_omvang | C11: Equity is the value of your assets minus debts, such as a mortgage. My equity | D11: far exceeds the need for regular spending in the future | E11: 3
A12: financiele_situatie | B12: eigen_vermogen_liquiditeit | C12: The equity can be freely investable and/or invested in real estate or other assets that are less easily tradable. My equity | D12: is only to a limited extent free to invest and consists of real estate (including the owner-occupied home) and/or less easily tradable assets | E12: 1
A13: financiele_situatie | B13: eigen_vermogen_liquiditeit | C13: The equity can be freely investable and/or invested in real estate or other assets that are less easily tradable. My equity | D13: is largely free to invest and consists partly of real estate (including the owner-occupied home) and/or less easily tradable assets | E13: 2 | F13: is largely free to invest and consists partly of real estate (including the owner-occupied home) and/or less easily tradable assets
A14: financiele_situatie | B14: eigen_vermogen_liquiditeit | C14: The equity can be freely investable and/or invested in real estate or other assets that are less easily tradable. My equity | D14: is free to invest | E14: 3
A15: financiele_situatie | B15: deel | C15: The part of the freely investable assets that I place with B.A. van Doorn | D15: is a quarter or less | E15: 3
A16: financiele_situatie | B16: deel | C16: The part of the freely investable assets that I place with B.A. van Doorn | D16: is about half | E16: 2 | F16: is about half
A17: financiele_situatie | B17: deel | C17: The part of the freely investable assets that I place with B.A. van Doorn | D17: more than half of the | E17: 1
A18: financiele_situatie | B18: inkomen | C18: My income (from salary, pension, enterprise or otherwise) | D18: is insufficient to live on and I have to make periodic withdrawals | E18: 1
A19: financiele_situatie | B19: inkomen | C19: My income (from salary, pension, enterprise or otherwise) | D19: is enough to live on, so I only have to make occasional withdrawals | E19: 2
A20: financiele_situatie | B20: inkomen | C20: My income (from salary, pension, enterprise or otherwise) | D20: is more than enough and I can grow my assets, except for possibly. Withdrawals for box 3 tax | E20: 3 | F20: is more than enough and I can grow my assets, except for possibly. Withdrawals for box 3 tax
A21: financiele_situatie | B21: gevolgen_materieel | C21: Purely financially, without having to adjust my spending habits, | D21: I can only have a limited decrease in the value of my investments | E21: 1
A22: financiele_situatie | B22: gevolgen_materieel | C22: Purely financially, without having to adjust my spending habits, | D22: I can handle a decrease in the value of my investments of about 25% | E22: 2 | F22: I can handle a decrease in the value of my investments of about 25%
A23: financiele_situatie | B23: gevolgen_materieel | C23: Purely financially, without having to adjust my spending habits, | D23: I can handle a drop in the value of my investments of up to 40% | E23: 3
A24: financiele_situatie | B24: huidige_samenstelling | C24: My current freely investable assets (i.e. in addition to my own home) | D24: consists mainly of savings and/or bonds | E24: 0
A25: financiele_situatie | B25: huidige_samenstelling | C25: My current freely investable assets (i.e. in addition to my own home) | D25: is invested in a portfolio of equities and bonds | E25: 0 | F25: is invested in a portfolio of equities and bonds
A26: financiele_situatie | B26: huidige_samenstelling | C26: My current freely investable assets (i.e. in addition to my own home) | D26: is mainly invested in shares and other risk-bearing investments | E26: 0
A27: kennis_ervaring | B27: kennis_beleggen | C27: My knowledge of investing | D27: is limited, I know little about it | E27: 1
A28: kennis_ervaring | B28: kennis_beleggen | C28: My knowledge of investing | D28: is average and I occasionally follow the financial news | E28: 2 | F28: is average and I occasionally follow the financial news
A29: kennis_ervaring | B29: kennis_beleggen | C29: My knowledge of investing | D29: is extensive and I follow the financial news closely | E29: 3
A30: kennis_ervaring | B30: kennis_instrumenten | C30: My knowledge of investment instruments | D30: is limited, I know little about it | E30: 1
A31: kennis_ervaring | B31: kennis_instrumenten | C31: My knowledge of investment instruments | D31: is present, I know what stocks and bonds are | E31: 2 | F31: is present, I know what stocks and bonds are
A32: kennis_ervaring | B32: kennis_instrumenten | C32: My knowledge of investment instruments | D32: is present, I know what stocks, bonds and alternative investments are | E32: 3
A33: kennis_ervaring | B33: ervaring_beleggingsdienstverlening | C33: With investment services | D33: I have no experience | E33: 1
A34: kennis_ervaring | B34: ervaring_beleggingsdienstverlening | C34: With investment services | D34: I have experience, especially with investment advice and/or execution only | E34: 3
A35: kennis_ervaring | B35: ervaring_beleggingsdienstverlening | C35: With investment services | D35: I have experience, especially with asset management | E35: 2 | F35: I have experience, especially with asset management
A36: kennis_ervaring | B36: ervaring_beleggen | C36: My experience with investing | D36: I have no experience with investing | E36: 1
A37: kennis_ervaring | B37: ervaring_beleggen | C37: My experience with investing | D37: is limited | E37: 2
A38: kennis_ervaring | B38: ervaring_beleggen | C38: My experience with investing | D38: is widely available | E38: 3 | F38: is widely available
A39: risicobereidheid | B39: gevolgen_emotioneel | C39: When it comes to poor investment results | D39: I can't stand that, emotionally speaking, | E39: 1
A40: risicobereidheid | B40: gevolgen_emotioneel | C40: When it comes to poor investment results | D40: am I willing, at some point, to accept about a 25% decrease in value | E40: 2 | F40: am I willing, at some point, to accept about a 25% decrease in value
A41: risicobereidheid | B41: gevolgen_emotioneel | C41: When it comes to poor investment results | D41: am I willing, at some point, to accept about a 40% decrease in value | E41: 3
A42: risicobereidheid | B42: hoe_vaak | C42: The value of my investments will fluctuate. | D42: I check it regularly and am on top of it | E42: 1 | F42: I check it regularly and am on top of it
A43: risicobereidheid | B43: hoe_vaak | C43: The value of my investments will fluctuate. | D43: I am waiting for the quarterly report | E43: 2
A44: risicobereidheid | B44: hoe_vaak | C44: The value of my investments will fluctuate. | D44: I watch once a year and less than once a quarter | E44: 3
A45: risicobereidheid | B45: beleggingshorizon | C45: Regarding my investment horizon, the following applies: | D45: I invest for about five years | E45: 1
A46: risicobereidheid | B46: beleggingshorizon | C46: Regarding my investment horizon, the following applies: | D46: I can hold my investments for ten years and have no interim plans with them | E46: 2 | F46: I can hold my investments for ten years and have no interim plans with them
A47: risicobereidheid | B47: beleggingshorizon | C47: Regarding my investment horizon, the following applies: | D47: I invest for a period longer than ten years | E47: 3
A48: risicobereidheid | B48: doel_niet_halen | C48: If I don't reach my investment objective | D48: That would be extremely disappointing | E48: 1
A49: risicobereidheid | B49: doel_niet_halen | C49: If I don't reach my investment objective | D49: That would be disappointing | E49: 2
A50: risicobereidheid | B50: doel_niet_halen | C50: If I don't reach my investment objective | D50: That can happen, because investing is associated with risks | E50: 3 | F50: That can happen, because investing is associated with risks
A51: duurzaamheid | B51: duurzaamheid_nu | C51: In the composition of my current investment portfolio | D51: sustainability doesn't play a role because I don't invest yet | E51: 0
A52: duurzaamheid | B52: duurzaamheid_nu | C52: In the composition of my current investment portfolio | D52: sustainability aspects do not play a special role | E52: 0 | F52: sustainability aspects do not play a special role
A53: duurzaamheid | B53: duurzaamheid_nu | C53: In the composition of my current investment portfolio | D53: sustainability aspects play a particular role in the | E53: 0
A54: duurzaamheid | B54: duurzaamheid_bavd | C54: When compiling my portfolio at B.A. van Doorn | D54: I don't have any sustainability preferences | E54: 0 | F54: =D54 -> I don't have any sustainability preferences
A55: duurzaamheid | B55: duurzaamheid_bavd | C55: When compiling my portfolio at B.A. van Doorn | D55: the principal adverse impacts on sustainability factors as mentioned above should be taken into account | E55: 0
A56: duurzaamheid | B56: duurzaamheid_percentage | C56: Regarding the sustainable investments part of our portfolio | D56: I want this to be more than a quarter | E56: 0 | F56: I want this to be more than a quarter
A57: duurzaamheid | B57: duurzaamheid_percentage | C57: Regarding the sustainable investments part of our portfolio | D57: I want this to be more than half | E57: 0
A58: duurzaamheid | B58: duurzaamheid_taxonomie | C58: So-called European Taxonomy investments | D58: are not a requirement for the filling of our portfolio | E58: 0 | F58: are not a requirement for the filling of our portfolio
A59: duurzaamheid | B59: duurzaamheid_taxonomie | C59: So-called European Taxonomy investments | D59: must account for more than 10% of the portfolio | E59: 0
A60: overig | B60: overig | C60: Would you like to explain other matters that have not been discussed? | D60: No, that's not necessary | E60: 0 | F60: No, that's not necessary
A61: overig | B61: overig | C61: Would you like to explain other matters that have not been discussed? | D61: Yes please - below a text box opens in which you can write an explanation | E61: 0
A62: private_beleggingen | B62: private_beleggingen | C62: Given the possible advantages and disadvantages of private investments mentioned, | D62: I would appreciate the inclusion of private investments in the portfolio | E62: 0 | F62: =D62 -> I would appreciate the inclusion of private investments in the portfolio
A63: private_beleggingen | B63: private_beleggingen | C63: Given the possible advantages and disadvantages of private investments mentioned, | D63: I am not interested in private investments | E63: 0

Sheet vragen_antwoorden_enof_nl
A1: categorie | B1: onderwerp | C1: vraag | D1: antwoord | E1: punten | F1: selected
A2: beleggingsdoelstelling | B2: beleggingsdoelstelling | C2: Wij willen ons vermogen beleggen | D2: zodat wij hiermee binnen afzienbare tijd een uitgave kunnen betalen - zie ook de invulvelden hieronder | E2: 1
A3: beleggingsdoelstelling | B3: beleggingsdoelstelling | C3: Wij willen ons vermogen beleggen | D3: om het grotendeels in stand te houden | E3: 2
A4: beleggingsdoelstelling | B4: beleggingsdoelstelling | C4: Wij willen ons vermogen beleggen | D4: om het zonder veel neerwaarts risico te beleggen, met kans op enige groei. | E4: 3
A5: beleggingsdoelstelling | B5: beleggingsdoelstelling | C5: Wij willen ons vermogen beleggen | D5: om het te laten groeien op de langere termijn | E5: 4 | F5: =D5 -> om het te laten groeien op de langere termijn
A6: beleggingsdoelstelling | B6: beleggingsdoelstelling | C6: Wij willen ons vermogen beleggen | D6: om op de lange termijn kans te hebben op het hoogste resultaat | E6: 5
A7: beleggingsdoelstelling | B7: beleggingsdoelstelling_toelichting | C7: Wilt u een toelichting geven op uw beleggingsdoelstelling? | D7: nee, dat is in het antwoord op de vorige vraag voldoende verwoord | E7: 0 | F7: =D7 -> nee, dat is in het antwoord op de vorige vraag voldoende verwoord
A8: beleggingsdoelstelling | B8: beleggingsdoelstelling_toelichting | C8: Wilt u een toelichting geven op uw beleggingsdoelstelling? | D8: ja graag - hieronder opent een tekstvakje waarin u een toelichting kunt schrijven | E8: 0
A9: financiele_situatie | B9: eigen_vermogen_omvang | C9: Eigen vermogen is de waarde van uw bezittingen minus de schulden, zoals een hypotheek. Ons eigen vermogen | D9: is niet voldoende om ons bestedingspatroon te kunnen handhaven | E9: 1
A10: financiele_situatie | B10: eigen_vermogen_omvang | C10: Eigen vermogen is de waarde van uw bezittingen minus de schulden, zoals een hypotheek. Ons eigen vermogen | D10: is voldoende om ons bestedingspatroon te handhaven | E10: 2 | F10: =D10 -> is voldoende om ons bestedingspatroon te handhaven
A11: financiele_situatie | B11: eigen_vermogen_omvang | C11: Eigen vermogen is de waarde van uw bezittingen minus de schulden, zoals een hypotheek. Ons eigen vermogen | D11: overstijgt ruimschoots de behoefte aan reguliere uitgaven in de toekomst | E11: 3
A12: financiele_situatie | B12: eigen_vermogen_liquiditeit | C12: Het eigen vermogen kan vrij belegbaar zijn en/of belegd zijn in vastgoed of andere minder makkelijk verhandelbare vermogensbestanddelen. Ons eigen vermogen | D12: is slechts beperkt vrij te beleggen en bestaat uit vastgoed (waaronder de eigen woning) en/of minder makkelijk verhandelbare vermogensbestanddelen | E12: 1
A13: financiele_situatie | B13: eigen_vermogen_liquiditeit | C13: Het eigen vermogen kan vrij belegbaar zijn en/of belegd zijn in vastgoed of andere minder makkelijk verhandelbare vermogensbestanddelen. Ons eigen vermogen | D13: is grotendeels vrij te beleggen en bestaat deels uit vastgoed (waaronder de eigen woning) en/of minder makkelijk verhandelbare vermogensbestanddelen | E13: 2
A14: financiele_situatie | B14: eigen_vermogen_liquiditeit | C14: Het eigen vermogen kan vrij belegbaar zijn en/of belegd zijn in vastgoed of andere minder makkelijk verhandelbare vermogensbestanddelen. Ons eigen vermogen | D14: is vrij te beleggen | E14: 3 | F14: =D14 -> is vrij te beleggen
A15: financiele_situatie | B15: deel | C15: Het deel van ons vrij belegbare vermogen dat wij bij B.A. van Doorn onderbrengen | D15: is een kwart of minder | E15: 3
A16: financiele_situatie | B16: deel | C16: Het deel van ons vrij belegbare vermogen dat wij bij B.A. van Doorn onderbrengen | D16: is ongeveer de helft | E16: 2 | F16: =D16 -> is ongeveer de helft
A17: financiele_situatie | B17: deel | C17: Het deel van ons vrij belegbare vermogen dat wij bij B.A. van Doorn onderbrengen | D17: is meer dan de helft | E17: 1
A18: financiele_situatie | B18: inkomen | C18: Ons inkomen (zoals uit loon, pensioen, of onderneming) | D18: is onvoldoende om van te leven en wij moeten periodiek onttrekkingen doen | E18: 1
A19: financiele_situatie | B19: inkomen | C19: Ons inkomen (zoals uit loon, pensioen, of onderneming) | D19: is genoeg om van te leven, waardoor wij slechts incidenteel onttrekkingen hoeven te doen | E19: 2
A20: financiele_situatie | B20: inkomen | C20: Ons inkomen (zoals uit loon, pensioen, of onderneming) | D20: is meer dan voldoende en wij kunnen ons vermogen laten groeien, behoudens evt. onttrekkingen voor box3-belasting | E20: 3 | F20: =D20 -> is meer dan voldoende en wij kunnen ons vermogen laten groeien, behoudens evt. onttrekkingen voor box3-belasting
A21: financiele_situatie | B21: gevolgen_materieel | C21: Louter financieel gezien, zonder ons bestedingspatroon te hoeven bijstellen, | D21: kunnen wij maar een beperkte waardedaling van ons beleggingen hebben | E21: 1
A22: financiele_situatie | B22: gevolgen_materieel | C22: Louter financieel gezien, zonder ons bestedingspatroon te hoeven bijstellen, | D22: kunnen wij een waardedaling van ons beleggingen aan van ongeveer 25% | E22: 2 | F22: =D22 -> kunnen wij een waardedaling van ons beleggingen aan van ongeveer 25%
A23: financiele_situatie | B23: gevolgen_materieel | C23: Louter financieel gezien, zonder ons bestedingspatroon te hoeven bijstellen, | D23: kunnen wij een waardedaling van ons beleggingen aan van wel zo'n 40% | E23: 3
A24: financiele_situatie | B24: huidige_samenstelling | C24: Ons huidige vrij belegbare vermogen (dus naast de eigen woning) | D24: bestaat overwegend uit spaargeld en/of obligaties | E24: 0
A25: financiele_situatie | B25: huidige_samenstelling | C25: Ons huidige vrij belegbare vermogen (dus naast de eigen woning) | D25: is belegd in een portefeuille aandelen en obligaties | E25: 0 | F25: =D25 -> is belegd in een portefeuille aandelen en obligaties
A26: financiele_situatie | B26: huidige_samenstelling | C26: Ons huidige vrij belegbare vermogen (dus naast de eigen woning) | D26: is vooral belegd in aandelen en andere risicodragende beleggingen | E26: 0
A27: kennis_ervaring | B27: kennis_beleggen | C27: Onze kennis van beleggen | D27: is beperkt, wij weten er weinig van | E27: 1
A28: kennis_ervaring | B28: kennis_beleggen | C28: Onze kennis van beleggen | D28: is gemiddeld en wij volgen af en toe het financiële nieuws | E28: 2 | F28: =D28 -> is gemiddeld en wij volgen af en toe het financiële nieuws
A29: kennis_ervaring | B29: kennis_beleggen | C29: Onze kennis van beleggen | D29: is uitgebreid en ik volg het financiële nieuws op de voet | E29: 3
A30: kennis_ervaring | B30: kennis_instrumenten | C30: Onze kennis van beleggingsinstrumenten | D30: is beperkt, wij weten er weinig van | E30: 1
A31: kennis_ervaring | B31: kennis_instrumenten | C31: Onze kennis van beleggingsinstrumenten | D31: is aanwezig, wij weten wat aandelen en obligaties zijn | E31: 2 | F31: =D31 -> is aanwezig, wij weten wat aandelen en obligaties zijn
A32: kennis_ervaring | B32: kennis_instrumenten | C32: Onze kennis van beleggingsinstrumenten | D32: is aanwezig, wij weten wat aandelen, obligaties en alternatieve beleggingen zijn | E32: 3
A33: kennis_ervaring | B33: ervaring_beleggingsdienstverlening | C33: Met beleggingsdienstverlening | D33: hebben wij geen ervaring | E33: 1
A34: kennis_ervaring | B34: ervaring_beleggingsdienstverlening | C34: Met beleggingsdienstverlening | D34: hebben wij ervaring, vooral met beleggingsadvies en/of execution only | E34: 3 | F34: =D34 -> hebben wij ervaring, vooral met beleggingsadvies en/of execution only
A35: kennis_ervaring | B35: ervaring_beleggingsdienstverlening | C35: Met beleggingsdienstverlening | D35: hebben wij ervaring, vooral met vermogensbeheer | E35: 2
A36: kennis_ervaring | B36: ervaring_beleggen | C36: Onze ervaring met beleggen | D36: Wij hebben geen ervaring met beleggen | E36: 1
A37: kennis_ervaring | B37: ervaring_beleggen | C37: Onze ervaring met beleggen | D37: is beperkt | E37: 2 | F37: =D37 -> is beperkt
A38: kennis_ervaring | B38: ervaring_beleggen | C38: Onze ervaring met beleggen | D38: is ruim aanwezig | E38: 3
A39: risicobereidheid | B39: gevolgen_emotioneel | C39: Als het gaat om slechte beleggingsresultaten | D39: daar kunnen wij, emotioneel gezien, niet goed tegen | E39: 1
A40: risicobereidheid | B40: gevolgen_emotioneel | C40: Als het gaat om slechte beleggingsresultaten | D40: zijn wij bereid, op enig moment, ongeveer 25% waardedaling te accepteren | E40: 2 | F40: =D40 -> zijn wij bereid, op enig moment, ongeveer 25% waardedaling te accepteren
A41: risicobereidheid | B41: gevolgen_emotioneel | C41: Als het gaat om slechte beleggingsresultaten | D41: zijn wij bereid, op enig moment, ongeveer 40% waardedaling te accepteren | E41: 3
A42: risicobereidheid | B42: hoe_vaak | C42: De waarde van onze beleggingen zal fluctueren. | D42: Wij checken het geregeld en zitten er bovenop | E42: 1
A43: risicobereidheid | B43: hoe_vaak | C43: De waarde van onze beleggingen zal fluctueren. | D43: Wij wachten de kwartaalrapportage af | E43: 2 | F43: =D43 -> Wij wachten de kwartaalrapportage af
A44: risicobereidheid | B44: hoe_vaak | C44: De waarde van onze beleggingen zal fluctueren. | D44: Wij kijken een keer per jaar en minder dan een keer per kwartaal | E44: 3
A45: risicobereidheid | B45: beleggingshorizon | C45: Wat betreft onze beleggingshorizon is het volgende van toepassing: | D45: Wij beleggen voor een jaar of vijf | E45: 1
A46: risicobereidheid | B46: beleggingshorizon | C46: Wat betreft onze beleggingshorizon is het volgende van toepassing: | D46: Wij kunnen onze beleggingen wel tien jaar aanhouden en hebben er geen tussentijdse plannen mee | E46: 2 | F46: =D46 -> Wij kunnen onze beleggingen wel tien jaar aanhouden en hebben er geen tussentijdse plannen mee
A47: risicobereidheid | B47: beleggingshorizon | C47: Wat betreft onze beleggingshorizon is het volgende van toepassing: | D47: Wij beleggen voor een periode langer dan tien jaar | E47: 3
A48: risicobereidheid | B48: doel_niet_halen | C48: Als wij onze beleggingsdoelstelling niet halen | D48: Dat zou buitengewoon teleurstellend zijn | E48: 1
A49: risicobereidheid | B49: doel_niet_halen | C49: Als wij onze beleggingsdoelstelling niet halen | D49: Dat zou teleurstellend zijn | E49: 2 | F49: =D49 -> Dat zou teleurstellend zijn
A50: risicobereidheid | B50: doel_niet_halen | C50: Als wij onze beleggingsdoelstelling niet halen | D50: Dat kan gebeuren, want beleggen gaat nu eenmaal gepaard met risico's | E50: 3
A51: duurzaamheid | B51: duurzaamheid_nu | C51: In de samenstelling van onze huidige beleggingsportefeuille | D51: speelt duurzaamheid geen rol want wij beleggen nog niet | E51: 0
A52: duurzaamheid | B52: duurzaamheid_nu | C52: In de samenstelling van onze huidige beleggingsportefeuille | D52: spelen duurzaamheidsaspecten geen bijzondere rol | E52: 0 | F52: =D52 -> spelen duurzaamheidsaspecten geen bijzondere rol
A53: duurzaamheid | B53: duurzaamheid_nu | C53: In de samenstelling van onze huidige beleggingsportefeuille | D53: spelen duurzaamheidsaspecten een bijzondere rol | E53: 0
A54: duurzaamheid | B54: duurzaamheid_bavd | C54: Bij de samenstelling van mijn portefeuille bij B.A. van Doorn | D54: hebben wij geen duurzaamheidsvoorkeuren | E54: 0 | F54: =D54 -> hebben wij geen duurzaamheidsvoorkeuren
A55: duurzaamheid | B55: duurzaamheid_bavd | C55: Bij de samenstelling van mijn portefeuille bij B.A. van Doorn | D55: moet rekening gehouden worden met de belangrijkste nadelige effecten op duurzaamheidsfactoren zoals hierboven genoemd | E55: 0
A56: duurzaamheid | B56: duurzaamheid_percentage | C56: Wat betreft het gedeelte duurzame beleggingen in onze portefeuille | D56: willen wij dat dit meer is dan een kwart | E56: 0 | F56: =D56 -> willen wij dat dit meer is dan een kwart
A57: duurzaamheid | B57: duurzaamheid_percentage | C57: Wat betreft het gedeelte duurzame beleggingen in onze portefeuille | D57: wil ik dat dit meer is dan de helft | E57: 0
A58: duurzaamheid | B58: duurzaamheid_taxonomie | C58: Zogenaamde Europese Taxonomie-beleggingen | D58: zijn geen vereiste voor de invulling van onze portefeuille | E58: 0 | F58: =D58 -> zijn geen vereiste voor de invulling van onze portefeuille
A59: duurzaamheid | B59: duurzaamheid_taxonomie | C59: Zogenaamde Europese Taxonomie-beleggingen | D59: moeten meer dan 10% uitmaken van de portfeuille | E59: 0
A60: overig | B60: overig | C60: Wilt u een toelichting geven op overige zaken die niet aan de orde zijn gekomen? | D60: nee, dat is niet nodig | E60: 0 | F60: =D60 -> nee, dat is niet nodig
A61: overig | B61: overig | C61: Wilt u een toelichting geven op overige zaken die niet aan de orde zijn gekomen? | D61: ja graag - hieronder opent een tekstvakje waarin u een toelichting kunt schrijven | E61: 0
A62: private_beleggingen | B62: private_beleggingen | C62: Gegeven de genoemde mogelijke voor- en nadelen van private beleggingen | D62: stellen wij prijs op het opnemen van private beleggingen in de portefeuille | E62: 0 | F62: stellen wij prijs op het opnemen van private beleggingen in de portefeuille
A63: private_beleggingen | B63: private_beleggingen | C63: Gegeven de genoemde mogelijke voor- en nadelen van private beleggingen | D63: hebben wij geen interesse in private beleggingen | E63: 0

Sheet vragen_antwoorden_enof_en
A1: categorie | B1: onderwerp | C1: vraag | D1: antwoord | E1: punten | F1: selected
A2: beleggingsdoelstelling | B2: beleggingsdoelstelling | C2: We want to invest our assets | D2: so that we can use it to pay for an expense in the foreseeable future - see also the input fields below | E2: 1
A3: beleggingsdoelstelling | B3: beleggingsdoelstelling | C3: We want to invest our assets | D3: to preserve it for the most part | E3: 2
A4: beleggingsdoelstelling | B4: beleggingsdoelstelling | C4: We want to invest our assets | D4: to invest it without much downside risk, with the chance of some growth. | E4: 3
A5: beleggingsdoelstelling | B5: beleggingsdoelstelling | C5: We want to invest our assets | D5: to grow it in the longer term | E5: 4 | F5: to grow it in the longer term
A6: beleggingsdoelstelling | B6: beleggingsdoelstelling | C6: We want to invest our assets | D6: to have a chance of achieving the highest result in the long term | E6: 5
A7: beleggingsdoelstelling | B7: beleggingsdoelstelling_toelichting | C7: Would you like to explain your investment objective? | D7: No, that is sufficiently expressed in the answer to the previous question | E7: 0 | F7: No, that is sufficiently expressed in the answer to the previous question
A8: beleggingsdoelstelling | B8: beleggingsdoelstelling_toelichting | C8: Would you like to explain your investment objective? | D8: Yes please - below a text box opens in which you can write an explanation | E8: 0
A9: financiele_situatie | B9: eigen_vermogen_omvang | C9: Equity is the value of your assets minus debts, such as a mortgage. Our equity | D9: is not enough to maintain our spending pattern | E9: 1
A10: financiele_situatie | B10: eigen_vermogen_omvang | C10: Equity is the value of your assets minus debts, such as a mortgage. Our equity | D10: is sufficient to maintain our spending pattern | E10: 2 | F10: is sufficient to maintain our spending pattern
A11: financiele_situatie | B11: eigen_vermogen_omvang | C11: Equity is the value of your assets minus debts, such as a mortgage. Our equity | D11: far exceeds the need for regular spending in the future | E11: 3
A12: financiele_situatie | B12: eigen_vermogen_liquiditeit | C12: The equity can be freely investable and/or invested in real estate or other assets that are less easily tradable. Our equity | D12: is only to a limited extent free to invest and consists of real estate (including the owner-occupied home) and/or less easily tradable assets | E12: 1
A13: financiele_situatie | B13: eigen_vermogen_liquiditeit | C13: The equity can be freely investable and/or invested in real estate or other assets that are less easily tradable. Our equity | D13: is largely free to invest and consists partly of real estate (including the owner-occupied home) and/or less easily tradable assets | E13: 2
A14: financiele_situatie | B14: eigen_vermogen_liquiditeit | C14: The equity can be freely investable and/or invested in real estate or other assets that are less easily tradable. Our equity | D14: is free to invest | E14: 3 | F14: is free to invest
A15: financiele_situatie | B15: deel | C15: The part of our freely investable assets that we place with B.A. van Doorn | D15: is a quarter or less | E15: 3
A16: financiele_situatie | B16: deel | C16: The part of our freely investable assets that we place with B.A. van Doorn | D16: is about half | E16: 2 | F16: is about half
A17: financiele_situatie | B17: deel | C17: The part of our freely investable assets that we place with B.A. van Doorn | D17: more than half of the | E17: 1
A18: financiele_situatie | B18: inkomen | C18: Our income (such as from wages, pensions, or businesses) | D18: is insufficient to live on and we have to make periodic withdrawals | E18: 1
A19: financiele_situatie | B19: inkomen | C19: Our income (such as from wages, pensions, or businesses) | D19: is enough to live on, so that we only have to make occasional withdrawals | E19: 2
A20: financiele_situatie | B20: inkomen | C20: Our income (such as from wages, pensions, or businesses) | D20: is more than sufficient and we can grow our assets, except for possibly. Withdrawals for box 3 tax | E20: 3 | F20: is more than sufficient and we can grow our assets, except for possibly. Withdrawals for box 3 tax
A21: financiele_situatie | B21: gevolgen_materieel | C21: From a purely financial point of view, without having to adjust our spending habits, | D21: we can only have a limited decrease in the value of our investments | E21: 1
A22: financiele_situatie | B22: gevolgen_materieel | C22: From a purely financial point of view, without having to adjust our spending habits, | D22: we can handle a decrease in the value of our investments of about 25% | E22: 2 | F22: we can handle a decrease in the value of our investments of about 25%
A23: financiele_situatie | B23: gevolgen_materieel | C23: From a purely financial point of view, without having to adjust our spending habits, | D23: we can handle a drop in the value of our investments of up to 40% | E23: 3
A24: financiele_situatie | B24: huidige_samenstelling | C24: Our current freely investable assets (i.e. in addition to our own home) | D24: consists mainly of savings and/or bonds | E24: 0
A25: financiele_situatie | B25: huidige_samenstelling | C25: Our current freely investable assets (i.e. in addition to our own home) | D25: is invested in a portfolio of equities and bonds | E25: 0 | F25: is invested in a portfolio of equities and bonds
A26: financiele_situatie | B26: huidige_samenstelling | C26: Our current freely investable assets (i.e. in addition to our own home) | D26: is mainly invested in shares and other risk-bearing investments | E26: 0
A27: kennis_ervaring | B27: kennis_beleggen | C27: Our knowledge of investing | D27: is limited, we know little about it | E27: 1
A28: kennis_ervaring | B28: kennis_beleggen | C28: Our knowledge of investing | D28: is average and we occasionally follow the financial news | E28: 2 | F28: is average and we occasionally follow the financial news
A29: kennis_ervaring | B29: kennis_beleggen | C29: Our knowledge of investing | D29: is extensive and I follow the financial news closely | E29: 3
A30: kennis_ervaring | B30: kennis_instrumenten | C30: Our knowledge of investment instruments | D30: is limited, we know little about it | E30: 1
A31: kennis_ervaring | B31: kennis_instrumenten | C31: Our knowledge of investment instruments | D31: is present, we know what stocks and bonds are | E31: 2 | F31: is present, we know what stocks and bonds are
A32: kennis_ervaring | B32: kennis_instrumenten | C32: Our knowledge of investment instruments | D32: is present, we know what shares, bonds and alternative investments are | E32: 3
A33: kennis_ervaring | B33: ervaring_beleggingsdienstverlening | C33: With investment services | D33: we have no experience | E33: 1
A34: kennis_ervaring | B34: ervaring_beleggingsdienstverlening | C34: With investment services | D34: we have experience, especially with investment advice and/or execution only | E34: 3 | F34: we have experience, especially with investment advice and/or execution only
A35: kennis_ervaring | B35: ervaring_beleggingsdienstverlening | C35: With investment services | D35: we have experience, especially with asset management | E35: 2
A36: kennis_ervaring | B36: ervaring_beleggen | C36: Our experience with investing | D36: We have no experience with investing | E36: 1
A37: kennis_ervaring | B37: ervaring_beleggen | C37: Our experience with investing | D37: is limited | E37: 2 | F37: is limited
A38: kennis_ervaring | B38: ervaring_beleggen | C38: Our experience with investing | D38: is widely available | E38: 3
A39: risicobereidheid | B39: gevolgen_emotioneel | C39: When it comes to poor investment results | D39: Emotionally, we can't handle that very well | E39: 1
A40: risicobereidheid | B40: gevolgen_emotioneel | C40: When it comes to poor investment results | D40: we are prepared, at any time, to accept about 25% decrease in value | E40: 2 | F40: we are prepared, at any time, to accept about 25% decrease in value
A41: risicobereidheid | B41: gevolgen_emotioneel | C41: When it comes to poor investment results | D41: we are prepared, at any time, to accept about 40% decrease in value | E41: 3
A42: risicobereidheid | B42: hoe_vaak | C42: The value of our investments will fluctuate. | D42: We check it regularly and are on top of it | E42: 1
A43: risicobereidheid | B43: hoe_vaak | C43: The value of our investments will fluctuate. | D43: We await the quarterly report | E43: 2 | F43: We await the quarterly report
A44: risicobereidheid | B44: hoe_vaak | C44: The value of our investments will fluctuate. | D44: We watch once a year and less than once a quarter | E44: 3
A45: risicobereidheid | B45: beleggingshorizon | C45: With regard to our investment horizon, the following applies: | D45: We invest for about five years | E45: 1
A46: risicobereidheid | B46: beleggingshorizon | C46: With regard to our investment horizon, the following applies: | D46: We can hold our investments for up to ten years and have no interim plans with them | E46: 2 | F46: We can hold our investments for up to ten years and have no interim plans with them
A47: risicobereidheid | B47: beleggingshorizon | C47: With regard to our investment horizon, the following applies: | D47: We invest for a period longer than ten years | E47: 3
A48: risicobereidheid | B48: doel_niet_halen | C48: If we don't achieve our investment objective | D48: That would be extremely disappointing | E48: 1
A49: risicobereidheid | B49: doel_niet_halen | C49: If we don't achieve our investment objective | D49: That would be disappointing | E49: 2 | F49: That would be disappointing
A50: risicobereidheid | B50: doel_niet_halen | C50: If we don't achieve our investment objective | D50: That can happen, because investing is associated with risks | E50: 3
A51: duurzaamheid | B51: duurzaamheid_nu | C51: In the composition of our current investment portfolio | D51: sustainability is not a factor because we are not yet investing | E51: 0
A52: duurzaamheid | B52: duurzaamheid_nu | C52: In the composition of our current investment portfolio | D52: sustainability aspects do not play a special role | E52: 0 | F52: sustainability aspects do not play a special role
A53: duurzaamheid | B53: duurzaamheid_nu | C53: In the composition of our current investment portfolio | D53: sustainability aspects play a particular role in the | E53: 0
A54: duurzaamheid | B54: duurzaamheid_bavd | C54: When compiling my portfolio at B.A. van Doorn | D54: we have no sustainability preferences | E54: 0 | F54: =D54 -> we have no sustainability preferences
A55: duurzaamheid | B55: duurzaamheid_bavd | C55: When compiling my portfolio at B.A. van Doorn | D55: the principal adverse impacts on sustainability factors as mentioned above should be taken into account | E55: 0
A56: duurzaamheid | B56: duurzaamheid_percentage | C56: Regarding the sustainable investments part of our portfolio | D56: we want this to be more than a quarter | E56: 0 | F56: we want this to be more than a quarter
A57: duurzaamheid | B57: duurzaamheid_percentage | C57: Regarding the sustainable investments part of our portfolio | D57: I want this to be more than half | E57: 0
A58: duurzaamheid | B58: duurzaamheid_taxonomie | C58: So-called European Taxonomy investments | D58: are not a requirement for the filling of our portfolio | E58: 0 | F58: are not a requirement for the filling of our portfolio
A59: duurzaamheid | B59: duurzaamheid_taxonomie | C59: So-called European Taxonomy investments | D59: must account for more than 10% of the portfolio | E59: 0
A60: overig | B60: overig | C60: Would you like to explain other matters that have not been discussed? | D60: No, that's not necessary | E60: 0 | F60: No, that's not necessary
A61: overig | B61: overig | C61: Would you like to explain other matters that have not been discussed? | D61: Yes please - below a text box opens in which you can write an explanation | E61: 0
A62: private_beleggingen | B62: private_beleggingen | C62: Given the possible advantages and disadvantages of private investments mentioned, | D62: we would appreciate the inclusion of private investments in the portfolio | E62: 0 | F62: =D62 -> we would appreciate the inclusion of private investments in the portfolio
A63: private_beleggingen | B63: private_beleggingen | C63: Given the possible advantages and disadvantages of private investments mentioned, | D63: we have no interest in private investments | E63: 0

Sheet vragen_antwoorden_bv_nl
A1: categorie | B1: onderwerp | C1: vraag | D1: antwoord | E1: punten | F1: selected
A2: beleggingsdoelstelling | B2: beleggingsdoelstelling | C2: Het vermogen in de besloten vennootschap wordt belegd | D2: om hiermee binnen afzienbare tijd een uitgave te doen | E2: 1
A3: beleggingsdoelstelling | B3: beleggingsdoelstelling | C3: Het vermogen in de besloten vennootschap wordt belegd | D3: om het grotendeels in stand te houden | E3: 2
A4: beleggingsdoelstelling | B4: beleggingsdoelstelling | C4: Het vermogen in de besloten vennootschap wordt belegd | D4: om het zonder veel neerwaarts risico te beleggen, met kans op enige groei | E4: 3
A5: beleggingsdoelstelling | B5: beleggingsdoelstelling | C5: Het vermogen in de besloten vennootschap wordt belegd | D5: om het te laten groeien op de langere termijn | E5: 4 | F5: =D5 -> om het te laten groeien op de langere termijn
A6: beleggingsdoelstelling | B6: beleggingsdoelstelling | C6: Het vermogen in de besloten vennootschap wordt belegd | D6: om op de lange termijn kans te hebben op het hoogste resultaat | E6: 5
A7: beleggingsdoelstelling | B7: beleggingsdoelstelling_toelichting | C7: Wilt u een toelichting geven op de beleggingsdoelstelling van de besloten vennootschap? | D7: nee, dat is in het antwoord op de vorige vraag voldoende verwoord | E7: 0 | F7: =D7 -> nee, dat is in het antwoord op de vorige vraag voldoende verwoord
A8: beleggingsdoelstelling | B8: beleggingsdoelstelling_toelichting | C8: Wilt u een toelichting geven op de beleggingsdoelstelling van de besloten vennootschap? | D8: ja graag - hieronder opent een tekstvakje waarin u een toelichting kunt schrijven | E8: 0
A9: financiele_situatie | B9: eigen_vermogen_liquiditeit | C9: Het vermogen in de besloten vennootschap | D9: is slechts beperkt vrij te beleggen en bestaat uit verstrekte leningen, vastgoed en/of andere minder makkelijk verhandelbare vermogensbestanddelen | E9: 1
A10: financiele_situatie | B10: eigen_vermogen_liquiditeit | C10: Het vermogen in de besloten vennootschap | D10: is grotendeels vrij te beleggen en bestaat deels uit vastgoed en/of minder makkelijk verhandelbare vermogensbestanddelen | E10: 2 | F10: =D10 -> is grotendeels vrij te beleggen en bestaat deels uit vastgoed en/of minder makkelijk verhandelbare vermogensbestanddelen
A11: financiele_situatie | B11: eigen_vermogen_liquiditeit | C11: Het vermogen in de besloten vennootschap | D11: is vrij te beleggen | E11: 3
A12: financiele_situatie | B12: deel | C12: Het deel van het vrij belegbare vermogen van de besloten vennootschap dat bij B.A. van Doorn in beheer komt | D12: is een kwart of minder | E12: 3
A13: financiele_situatie | B13: deel | C13: Het deel van het vrij belegbare vermogen van de besloten vennootschap dat bij B.A. van Doorn in beheer komt | D13: is ongeveer de helft | E13: 2 | F13: =D13 -> is ongeveer de helft
A14: financiele_situatie | B14: deel | C14: Het deel van het vrij belegbare vermogen van de besloten vennootschap dat bij B.A. van Doorn in beheer komt | D14: is meer dan de helft | E14: 1
A15: financiele_situatie | B15: inkomen | C15: Aanvullend inkomen uit de besloten vennootschap voor privédoeleinden | D15: is noodzakelijk om van te leven en ik moet periodiek onttrekkingen doen uit de besloten vennootschap | E15: 1
A16: financiele_situatie | B16: inkomen | C16: Aanvullend inkomen uit de besloten vennootschap voor privédoeleinden | D16: is soms noodzakelijk, waardoor ik incidenteel onttrekkingen moet doen uit de besloten vennootschap | E16: 2
A17: financiele_situatie | B17: inkomen | C17: Aanvullend inkomen uit de besloten vennootschap voor privédoeleinden | D17: is niet noodzakelijk en het vermogen in de besloten vennootschap kan blijven groeien, behoudens evt. onttrekkingen voor het betalen van belasting | E17: 3 | F17: =D17 -> is niet noodzakelijk en het vermogen in de besloten vennootschap kan blijven groeien, behoudens evt. onttrekkingen voor het betalen van belasting
A18: financiele_situatie | B18: gevolgen_materieel | C18: Louter financieel gezien, dus zonder verdere nadelige consequenties | D18: kan ik maar een beperkte waardedaling hebben van de beleggingen in de besloten vennootschap | E18: 1
A19: financiele_situatie | B19: gevolgen_materieel | C19: Louter financieel gezien, dus zonder verdere nadelige consequenties | D19: kan ik een waardedaling van ongeveer 25% aan van mijn beleggingen in de besloten vennootschap | E19: 2 | F19: =D19 -> kan ik een waardedaling van ongeveer 25% aan van mijn beleggingen in de besloten vennootschap
A20: financiele_situatie | B20: gevolgen_materieel | C20: Louter financieel gezien, dus zonder verdere nadelige consequenties | D20: kan ik een waardedaling van wel zo'n 40% aan van mijn beleggingen in de besloten vennootschap | E20: 3
A21: financiele_situatie | B21: huidige_samenstelling | C21: Het huidige vrij belegbare vermogen van de besloten vennootschap | D21: bestaat overwegend uit spaargeld en/of obligaties | E21: 0
A22: financiele_situatie | B22: huidige_samenstelling | C22: Het huidige vrij belegbare vermogen van de besloten vennootschap | D22: is belegd in een portefeuille aandelen en obligaties | E22: 0 | F22: =D22 -> is belegd in een portefeuille aandelen en obligaties
A23: financiele_situatie | B23: huidige_samenstelling | C23: Het huidige vrij belegbare vermogen van de besloten vennootschap | D23: is vooral belegd in aandelen en andere risicodragende beleggingen | E23: 0
A24: kennis_ervaring | B24: kennis_beleggen | C24: Mijn kennis van beleggen | D24: is beperkt, ik weet er weinig van | E24: 1
A25: kennis_ervaring | B25: kennis_beleggen | C25: Mijn kennis van beleggen | D25: is gemiddeld en ik volg af en toe het financiële nieuws | E25: 2 | F25: =D25 -> is gemiddeld en ik volg af en toe het financiële nieuws
A26: kennis_ervaring | B26: kennis_beleggen | C26: Mijn kennis van beleggen | D26: is uitgebreid en ik volg het financiële nieuws op de voet | E26: 3
A27: kennis_ervaring | B27: kennis_instrumenten | C27: Mijn kennis van beleggingsinstrumenten | D27: is beperkt, ik weet er weinig van | E27: 1
A28: kennis_ervaring | B28: kennis_instrumenten | C28: Mijn kennis van beleggingsinstrumenten | D28: is aanwezig, ik weet wat aandelen en obligaties zijn | E28: 2 | F28: =D28 -> is aanwezig, ik weet wat aandelen en obligaties zijn
A29: kennis_ervaring | B29: kennis_instrumenten | C29: Mijn kennis van beleggingsinstrumenten | D29: is uitgebreid en ik volg het financiële nieuws op de voet | E29: 3
A30: kennis_ervaring | B30: ervaring_beleggingsdienstverlening | C30: Met beleggingsdienstverlening | D30: heb ik geen ervaring | E30: 1
A31: kennis_ervaring | B31: ervaring_beleggingsdienstverlening | C31: Met beleggingsdienstverlening | D31: heb ik ervaring, vooral met beleggingsadvies en/of execution only | E31: 3
A32: kennis_ervaring | B32: ervaring_beleggingsdienstverlening | C32: Met beleggingsdienstverlening | D32: heb ik ervaring, vooral met vermogensbeheer | E32: 2 | F32: =D32 -> heb ik ervaring, vooral met vermogensbeheer
A33: kennis_ervaring | B33: ervaring_beleggen | C33: Mijn ervaring met beleggen | D33: Ik heb geen ervaring met beleggen | E33: 1
A34: kennis_ervaring | B34: ervaring_beleggen | C34: Mijn ervaring met beleggen | D34: is beperkt | E34: 2
A35: kennis_ervaring | B35: ervaring_beleggen | C35: Mijn ervaring met beleggen | D35: is ruim aanwezig | E35: 3 | F35: =D35 -> is ruim aanwezig
A36: risicobereidheid | B36: gevolgen_emotioneel | C36: Als het gaat om slechte beleggingsresultaten in de besloten vennootschap | D36: daar kan ik, emotioneel gezien, niet goed tegen | E36: 1
A37: risicobereidheid | B37: gevolgen_emotioneel | C37: Als het gaat om slechte beleggingsresultaten in de besloten vennootschap | D37: ben ik bereid, op enig moment, ongeveer 25% waardedaling te accepteren | E37: 2 | F37: =D37 -> ben ik bereid, op enig moment, ongeveer 25% waardedaling te accepteren
A38: risicobereidheid | B38: gevolgen_emotioneel | C38: Als het gaat om slechte beleggingsresultaten in de besloten vennootschap | D38: ben ik bereid, op enig moment, ongeveer 40% waardedaling te accepteren | E38: 3
A39: risicobereidheid | B39: hoe_vaak | C39: De waarde van de beleggingen in de besloten vennootschap zal fluctueren. | D39: Ik check het geregeld en zit er bovenop | E39: 1 | F39: =D39 -> Ik check het geregeld en zit er bovenop
A40: risicobereidheid | B40: hoe_vaak | C40: De waarde van de beleggingen in de besloten vennootschap zal fluctueren. | D40: Ik wacht de kwartaalrapportage af | E40: 2
A41: risicobereidheid | B41: hoe_vaak | C41: De waarde van de beleggingen in de besloten vennootschap zal fluctueren. | D41: Ik kijk een keer per jaar en minder dan een keer per kwartaal | E41: 3
A42: risicobereidheid | B42: beleggingshorizon | C42: Wat betreft de beleggingshorizon is het volgende van toepassing: | D42: de belegging in de besloten vennootschap wordt gedaan voor een jaar of vijf | E42: 1
A43: risicobereidheid | B43: beleggingshorizon | C43: Wat betreft de beleggingshorizon is het volgende van toepassing: | D43: de beleggingen in de besloten vennootschap kunnen wel tien jaar aangehouden worden en er zijn geen tussentijdse plannen mee | E43: 2 | F43: =D43 -> de beleggingen in de besloten vennootschap kunnen wel tien jaar aangehouden worden en er zijn geen tussentijdse plannen mee
A44: risicobereidheid | B44: beleggingshorizon | C44: Wat betreft de beleggingshorizon is het volgende van toepassing: | D44: de beleggingen in de besloten vennootschap worden gedaan voor een periode langer dan tien jaar | E44: 3
A45: risicobereidheid | B45: doel_niet_halen | C45: Als de beleggingsdoelstelling van de besloten vennootschap niet gehaald wordt | D45: Dat zou buitengewoon teleurstellend zijn | E45: 1
A46: risicobereidheid | B46: doel_niet_halen | C46: Als de beleggingsdoelstelling van de besloten vennootschap niet gehaald wordt | D46: Dat zou teleurstellend zijn | E46: 2
A47: risicobereidheid | B47: doel_niet_halen | C47: Als de beleggingsdoelstelling van de besloten vennootschap niet gehaald wordt | D47: Dat kan gebeuren, want beleggen gaat nu eenmaal gepaard met risico's | E47: 3 | F47: =D47 -> Dat kan gebeuren, want beleggen gaat nu eenmaal gepaard met risico's
A48: duurzaamheid | B48: duurzaamheid_nu | C48: In de samenstelling van de huidige beleggingsportefeuille van de besloten vennootschap | D48: speelt duurzaamheid geen rol want er zijn nog geen beleggingen | E48: 0
A49: duurzaamheid | B49: duurzaamheid_nu | C49: In de samenstelling van de huidige beleggingsportefeuille van de besloten vennootschap | D49: spelen duurzaamheidsaspecten geen bijzondere rol | E49: 0 | F49: =D49 -> spelen duurzaamheidsaspecten geen bijzondere rol
A50: duurzaamheid | B50: duurzaamheid_nu | C50: In de samenstelling van de huidige beleggingsportefeuille van de besloten vennootschap | D50: spelen duurzaamheidsaspecten een bijzondere rol | E50: 0
A51: duurzaamheid | B51: duurzaamheid_bavd | C51: Bij de samenstelling van de portefeuille bij B.A. van Doorn | D51: bestaan geen duurzaamheidsvoorkeuren | E51: 0 | F51: =D51 -> bestaan geen duurzaamheidsvoorkeuren
A52: duurzaamheid | B52: duurzaamheid_bavd | C52: Bij de samenstelling van de portefeuille bij B.A. van Doorn | D52: moet rekening gehouden worden met de belangrijkste nadelige effecten op duurzaamheidsfactoren zoals hierboven genoemd | E52: 0
A53: duurzaamheid | B53: duurzaamheid_percentage | C53: Wat betreft het gedeelte duurzame beleggingen in de portefeuille van de besloten vennootschap | D53: moet dit meer zijn dan een kwart | E53: 0 | F53: =D53 -> moet dit meer zijn dan een kwart
A54: duurzaamheid | B54: duurzaamheid_percentage | C54: Wat betreft het gedeelte duurzame beleggingen in de portefeuille van de besloten vennootschap | D54: moet dit meer zijn dan de helft | E54: 0
A55: duurzaamheid | B55: duurzaamheid_taxonomie | C55: Zogenaamde Europese Taxonomie-beleggingen | D55: zijn geen vereiste voor de invulling van de portefeuille | E55: 0 | F55: =D55 -> zijn geen vereiste voor de invulling van de portefeuille
A56: duurzaamheid | B56: duurzaamheid_taxonomie | C56: Zogenaamde Europese Taxonomie-beleggingen | D56: moeten meer dan 10% uitmaken van de portfeuille | E56: 0
A57: overig | B57: overig | C57: Wilt u een toelichting geven op overige zaken die niet aan de orde zijn gekomen? | D57: nee, dat is niet nodig | E57: 0 | F57: =D57 -> nee, dat is niet nodig
A58: overig | B58: overig | C58: Wilt u een toelichting geven op overige zaken die niet aan de orde zijn gekomen? | D58: ja graag - hieronder opent een tekstvakje waarin u een toelichting kunt schrijven | E58: 0
A59: private_beleggingen | B59: private_beleggingen | C59: Gegeven de genoemde mogelijke voor- en nadelen van private beleggingen | D59: stel ik prijs op het opnemen van private beleggingen in de portefeuille van de bv | E59: 0 | F59: stel ik prijs op het opnemen van private beleggingen in de portefeuille van de bv
A60: private_beleggingen | B60: private_beleggingen | C60: Gegeven de genoemde mogelijke voor- en nadelen van private beleggingen | D60: heb ik geen interesse in private beleggingen voor de bv | E60: 0

Sheet vragen_antwoorden_bv_en
A1: categorie | B1: onderwerp | C1: vraag | D1: antwoord | E1: punten | F1: selected
A2: beleggingsdoelstelling | B2: beleggingsdoelstelling | C2: The assets in the private limited company are invested | D2: to make an expense with this in the foreseeable future | E2: 1
A3: beleggingsdoelstelling | B3: beleggingsdoelstelling | C3: The assets in the private limited company are invested | D3: to preserve it for the most part | E3: 2
A4: beleggingsdoelstelling | B4: beleggingsdoelstelling | C4: The assets in the private limited company are invested | D4: to invest it without much downside risk, with the potential for some growth | E4: 3
A5: beleggingsdoelstelling | B5: beleggingsdoelstelling | C5: The assets in the private limited company are invested | D5: to grow it in the longer term | E5: 4 | F5: =D5 -> to grow it in the longer term
A6: beleggingsdoelstelling | B6: beleggingsdoelstelling | C6: The assets in the private limited company are invested | D6: to have a chance of achieving the highest result in the long term | E6: 5
A7: beleggingsdoelstelling | B7: beleggingsdoelstelling_toelichting | C7: Would you like to explain the investment objective of the private limited company? | D7: No, that is sufficiently expressed in the answer to the previous question | E7: 0 | F7: =D7 -> No, that is sufficiently expressed in the answer to the previous question
A8: beleggingsdoelstelling | B8: beleggingsdoelstelling_toelichting | C8: Would you like to explain the investment objective of the private limited company? | D8: Yes please - below a text box opens in which you can write an explanation | E8: 0
A9: financiele_situatie | B9: eigen_vermogen_liquiditeit | C9: The assets in the private limited company | D9: is only free to invest to a limited extent and consists of loans, real estate and/or other assets that are less easily tradable | E9: 1
A10: financiele_situatie | B10: eigen_vermogen_liquiditeit | C10: The assets in the private limited company | D10: is largely free to invest and partly consists of real estate and/or less easily tradable assets | E10: 2 | F10: =D10 -> is largely free to invest and partly consists of real estate and/or less easily tradable assets
A11: financiele_situatie | B11: eigen_vermogen_liquiditeit | C11: The assets in the private limited company | D11: is free to invest | E11: 3
A12: financiele_situatie | B12: deel | C12: The part of the freely investable assets of the private limited company that will be managed by B.A. van Doorn | D12: is a quarter or less | E12: 3
A13: financiele_situatie | B13: deel | C13: The part of the freely investable assets of the private limited company that will be managed by B.A. van Doorn | D13: is about half | E13: 2 | F13: =D13 -> is about half
A14: financiele_situatie | B14: deel | C14: The part of the freely investable assets of the private limited company that will be managed by B.A. van Doorn | D14: more than half of the | E14: 1
A15: financiele_situatie | B15: inkomen | C15: Supplementary income from the private limited company for private purposes | D15: is necessary to live on and I have to make periodic withdrawals from the private limited company | E15: 1
A16: financiele_situatie | B16: inkomen | C16: Supplementary income from the private limited company for private purposes | D16: is sometimes necessary, as a result of which I occasionally have to make withdrawals from the private limited company | E16: 2
A17: financiele_situatie | B17: inkomen | C17: Supplementary income from the private limited company for private purposes | D17: is not necessary and the assets in the private limited company can continue to grow, except in the case of possibly. withdrawals for the payment of tax | E17: 3 | F17: =D17 -> is not necessary and the assets in the private limited company can continue to grow, except in the case of possibly. withdrawals for the payment of tax
A18: financiele_situatie | B18: gevolgen_materieel | C18: Purely financially, so without further adverse consequences | D18: I can only have a limited decrease in the value of the investments in the private limited company | E18: 1
A19: financiele_situatie | B19: gevolgen_materieel | C19: Purely financially, so without further adverse consequences | D19: I can handle a decrease in value of about 25% of my investments in the private limited company | E19: 2 | F19: =D19 -> I can handle a decrease in value of about 25% of my investments in the private limited company
A20: financiele_situatie | B20: gevolgen_materieel | C20: Purely financially, so without further adverse consequences | D20: I can handle a decrease in value of up to 40% of my investments in the private limited company | E20: 3
A21: financiele_situatie | B21: huidige_samenstelling | C21: The current freely investable assets of the private limited company | D21: consists mainly of savings and/or bonds | E21: 0
A22: financiele_situatie | B22: huidige_samenstelling | C22: The current freely investable assets of the private limited company | D22: is invested in a portfolio of equities and bonds | E22: 0 | F22: =D22 -> is invested in a portfolio of equities and bonds
A23: financiele_situatie | B23: huidige_samenstelling | C23: The current freely investable assets of the private limited company | D23: is mainly invested in shares and other risk-bearing investments | E23: 0
A24: kennis_ervaring | B24: kennis_beleggen | C24: My knowledge of investing | D24: is limited, I know little about it | E24: 1
A25: kennis_ervaring | B25: kennis_beleggen | C25: My knowledge of investing | D25: is average and I occasionally follow the financial news | E25: 2 | F25: =D25 -> is average and I occasionally follow the financial news
A26: kennis_ervaring | B26: kennis_beleggen | C26: My knowledge of investing | D26: is extensive and I follow the financial news closely | E26: 3
A27: kennis_ervaring | B27: kennis_instrumenten | C27: My knowledge of investment instruments | D27: is limited, I know little about it | E27: 1
A28: kennis_ervaring | B28: kennis_instrumenten | C28: My knowledge of investment instruments | D28: is present, I know what stocks and bonds are | E28: 2 | F28: =D28 -> is present, I know what stocks and bonds are
A29: kennis_ervaring | B29: kennis_instrumenten | C29: My knowledge of investment instruments | D29: is extensive and I follow the financial news closely | E29: 3
A30: kennis_ervaring | B30: ervaring_beleggingsdienstverlening | C30: With investment services | D30: I have no experience | E30: 1
A31: kennis_ervaring | B31: ervaring_beleggingsdienstverlening | C31: With investment services | D31: I have experience, especially with investment advice and/or execution only | E31: 3
A32: kennis_ervaring | B32: ervaring_beleggingsdienstverlening | C32: With investment services | D32: I have experience, especially with asset management | E32: 2 | F32: =D32 -> I have experience, especially with asset management
A33: kennis_ervaring | B33: ervaring_beleggen | C33: My experience with investing | D33: I have no experience with investing | E33: 1
A34: kennis_ervaring | B34: ervaring_beleggen | C34: My experience with investing | D34: is limited | E34: 2
A35: kennis_ervaring | B35: ervaring_beleggen | C35: My experience with investing | D35: is widely available | E35: 3 | F35: =D35 -> is widely available
A36: risicobereidheid | B36: gevolgen_emotioneel | C36: When it comes to poor investment results in the private limited company | D36: I can't stand that, emotionally speaking, | E36: 1
A37: risicobereidheid | B37: gevolgen_emotioneel | C37: When it comes to poor investment results in the private limited company | D37: am I willing, at some point, to accept about a 25% decrease in value | E37: 2 | F37: =D37 -> am I willing, at some point, to accept about a 25% decrease in value
A38: risicobereidheid | B38: gevolgen_emotioneel | C38: When it comes to poor investment results in the private limited company | D38: am I willing, at some point, to accept about a 40% decrease in value | E38: 3
A39: risicobereidheid | B39: hoe_vaak | C39: The value of the investments in the private limited company will fluctuate. | D39: I check it regularly and am on top of it | E39: 1 | F39: =D39 -> I check it regularly and am on top of it
A40: risicobereidheid | B40: hoe_vaak | C40: The value of the investments in the private limited company will fluctuate. | D40: I am waiting for the quarterly report | E40: 2
A41: risicobereidheid | B41: hoe_vaak | C41: The value of the investments in the private limited company will fluctuate. | D41: I watch once a year and less than once a quarter | E41: 3
A42: risicobereidheid | B42: beleggingshorizon | C42: With regard to the investment horizon, the following applies: | D42: the investment in the private limited company is made for about five years | E42: 1
A43: risicobereidheid | B43: beleggingshorizon | C43: With regard to the investment horizon, the following applies: | D43: The investments in the private limited company can be held for up to ten years and there are no interim plans | E43: 2 | F43: =D43 -> The investments in the private limited company can be held for up to ten years and there are no interim plans
A44: risicobereidheid | B44: beleggingshorizon | C44: With regard to the investment horizon, the following applies: | D44: the investments in the private limited liability company are made for a period longer than ten years | E44: 3
A45: risicobereidheid | B45: doel_niet_halen | C45: If the investment objective of the private limited company is not achieved | D45: That would be extremely disappointing | E45: 1
A46: risicobereidheid | B46: doel_niet_halen | C46: If the investment objective of the private limited company is not achieved | D46: That would be disappointing | E46: 2
A47: risicobereidheid | B47: doel_niet_halen | C47: If the investment objective of the private limited company is not achieved | D47: That can happen, because investing is associated with risks | E47: 3 | F47: =D47 -> That can happen, because investing is associated with risks
A48: duurzaamheid | B48: duurzaamheid_nu | C48: In the composition of the private limited company's current investment portfolio | D48: sustainability does not play a role because there are no investments yet | E48: 0
A49: duurzaamheid | B49: duurzaamheid_nu | C49: In the composition of the private limited company's current investment portfolio | D49: sustainability aspects do not play a special role | E49: 0 | F49: =D49 -> sustainability aspects do not play a special role
A50: duurzaamheid | B50: duurzaamheid_nu | C50: In the composition of the private limited company's current investment portfolio | D50: sustainability aspects play a particular role in the | E50: 0
A51: duurzaamheid | B51: duurzaamheid_bavd | C51: In the composition of the portfolio at B.A. van Doorn | D51: there are no sustainability preferences | E51: 0 | F51: =D51 -> there are no sustainability preferences
A52: duurzaamheid | B52: duurzaamheid_bavd | C52: In the composition of the portfolio at B.A. van Doorn | D52: the principal adverse impacts on sustainability factors as mentioned above should be taken into account | E52: 0
A53: duurzaamheid | B53: duurzaamheid_percentage | C53: With regard to the sustainable investments part of the private limited company's portfolio | D53: this must be more than a quarter | E53: 0 | F53: =D53 -> this must be more than a quarter
A54: duurzaamheid | B54: duurzaamheid_percentage | C54: With regard to the sustainable investments part of the private limited company's portfolio | D54: this must be more than half | E54: 0
A55: duurzaamheid | B55: duurzaamheid_taxonomie | C55: So-called European Taxonomy investments | D55: are not a requirement for the completion of the portfolio | E55: 0 | F55: =D55 -> are not a requirement for the completion of the portfolio
A56: duurzaamheid | B56: duurzaamheid_taxonomie | C56: So-called European Taxonomy investments | D56: must account for more than 10% of the portfolio | E56: 0
A57: overig | B57: overig | C57: Would you like to explain other matters that have not been discussed? | D57: No, that's not necessary | E57: 0 | F57: =D57 -> No, that's not necessary
A58: overig | B58: overig | C58: Would you like to explain other matters that have not been discussed? | D58: Yes please - below a text box opens in which you can write an explanation | E58: 0
A59: private_beleggingen | B59: private_beleggingen | C59: Given the possible advantages and disadvantages of private investments mentioned, | D59: I would appreciate including private investments in the portfolio of the BV | E59: 0 | F59: =D59 -> I would appreciate including private investments in the portfolio of the BV
A60: private_beleggingen | B60: private_beleggingen | C60: Given the possible advantages and disadvantages of private investments mentioned, | D60: I am not interested in private investments for the BV | E60: 0

Sheet vragen_antwoorden_ve_nl
A1: categorie | B1: onderwerp | C1: vraag | D1: antwoord | E1: punten | F1: selected
A2: beleggingsdoelstelling | B2: beleggingsdoelstelling | C2: Het vermogen van de vereniging wordt belegd | D2: om hiermee binnen afzienbare tijd een uitgave te betalen - zie ook de invulvelden hieronder | E2: 1
A3: beleggingsdoelstelling | B3: beleggingsdoelstelling | C3: Het vermogen van de vereniging wordt belegd | D3: om het grotendeels in stand te houden | E3: 2
A4: beleggingsdoelstelling | B4: beleggingsdoelstelling | C4: Het vermogen van de vereniging wordt belegd | D4: om het zonder veel neerwaarts risico te beleggen, met kans op enige groei. | E4: 3
A5: beleggingsdoelstelling | B5: beleggingsdoelstelling | C5: Het vermogen van de vereniging wordt belegd | D5: om het te laten groeien op de langere termijn | E5: 4 | F5: =D5 -> om het te laten groeien op de langere termijn
A6: beleggingsdoelstelling | B6: beleggingsdoelstelling | C6: Het vermogen van de vereniging wordt belegd | D6: om op de lange termijn kans te hebben op het hoogste resultaat | E6: 5
A7: beleggingsdoelstelling | B7: beleggingsdoelstelling_toelichting | C7: Wilt u een toelichting geven op de beleggingsdoelstelling van de vereniging (bijvoorbeeld aan de hand van een beleggingsstatuut)? | D7: nee, dat is in het antwoord op de vorige vraag voldoende verwoord | E7: 0 | F7: =D7 -> nee, dat is in het antwoord op de vorige vraag voldoende verwoord
A8: beleggingsdoelstelling | B8: beleggingsdoelstelling_toelichting | C8: Wilt u een toelichting geven op de beleggingsdoelstelling van de vereniging (bijvoorbeeld aan de hand van een beleggingsstatuut)? | D8: ja graag - hieronder opent een tekstvakje waarin u een toelichting kunt schrijven | E8: 0
A9: financiele_situatie | B9: eigen_vermogen_omvang | C9: Eigen vermogen is de waarde van de bezittingen minus de schulden, zoals een lening. Het eigen vermogen van de vereniging | D9: is niet voldoende om de verwachte minimale kasstroom te kunnen handhaven | E9: 1 | F9: =D9 -> is niet voldoende om de verwachte minimale kasstroom te kunnen handhaven
A10: financiele_situatie | B10: eigen_vermogen_omvang | C10: Eigen vermogen is de waarde van de bezittingen minus de schulden, zoals een lening. Het eigen vermogen van de vereniging | D10: is voldoende om de verwachte minimale kasstroom te handhaven | E10: 2
A11: financiele_situatie | B11: eigen_vermogen_omvang | C11: Eigen vermogen is de waarde van de bezittingen minus de schulden, zoals een lening. Het eigen vermogen van de vereniging | D11: overstijgt ruimschoots de verwachte minimale kasstroom in de toekomst | E11: 3
A12: financiele_situatie | B12: eigen_vermogen_liquiditeit | C12: Het eigen vermogen kan vrij belegbaar zijn en/of belegd zijn in vastgoed of andere minder makkelijk verhandelbare vermogensbestanddelen. Het vrije vermogen van de vereniging | D12: is slechts beperkt vrij te beleggen en bestaat uit verstrekte leningen, vastgoed en/of andere minder makkelijk verhandelbare vermogensbestanddelen | E12: 1
A13: financiele_situatie | B13: eigen_vermogen_liquiditeit | C13: Het eigen vermogen kan vrij belegbaar zijn en/of belegd zijn in vastgoed of andere minder makkelijk verhandelbare vermogensbestanddelen. Het vrije vermogen van de vereniging | D13: is grotendeels vrij te beleggen en bestaat deels uit vastgoed en/of minder makkelijk verhandelbare vermogensbestanddelen | E13: 2 | F13: =D13 -> is grotendeels vrij te beleggen en bestaat deels uit vastgoed en/of minder makkelijk verhandelbare vermogensbestanddelen
A14: financiele_situatie | B14: eigen_vermogen_liquiditeit | C14: Het eigen vermogen kan vrij belegbaar zijn en/of belegd zijn in vastgoed of andere minder makkelijk verhandelbare vermogensbestanddelen. Het vrije vermogen van de vereniging | D14: is vrij te beleggen | E14: 3
A15: financiele_situatie | B15: deel | C15: Het deel van het vrij belegbare vermogen van de vereniging dat bij B.A. van Doorn in beheer komt | D15: is een kwart of minder | E15: 3
A16: financiele_situatie | B16: deel | C16: Het deel van het vrij belegbare vermogen van de vereniging dat bij B.A. van Doorn in beheer komt | D16: is ongeveer de helft | E16: 2 | F16: =D16 -> is ongeveer de helft
A17: financiele_situatie | B17: deel | C17: Het deel van het vrij belegbare vermogen van de vereniging dat bij B.A. van Doorn in beheer komt | D17: is meer dan de helft | E17: 1
A18: financiele_situatie | B18: inkomen | C18: Het inkomen van de vereniging (zoals uit contributies, schenkingen of subsidies) | D18: is onvoldoende om de kosten van de vereniging te dragen en jaarlijkse onttrekkingen uit de beleggingen zijn noodzakelijk | E18: 1
A19: financiele_situatie | B19: inkomen | C19: Het inkomen van de vereniging (zoals uit contributies, schenkingen of subsidies) | D19: is voldoende om de kosten te dragen, waardoor slechts incidenteel onttrekkingen uit de portefeuille noodzakelijk zijn | E19: 2
A20: financiele_situatie | B20: inkomen | C20: Het inkomen van de vereniging (zoals uit contributies, schenkingen of subsidies) | D20: is meer dan voldoende en het vermogen van de vereniging kan blijven groeien, behoudens evt. onttrekkingen voor incidentele uitgaven | E20: 3 | F20: =D20 -> is meer dan voldoende en het vermogen van de vereniging kan blijven groeien, behoudens evt. onttrekkingen voor incidentele uitgaven
A21: financiele_situatie | B21: gevolgen_materieel | C21: Louter financieel gezien, zonder aanpassingen te hoeven doen aan het jaarlijks te besteden budget | D21: kan de vereniging maar een beperkte waardedaling hebben van de beleggingen | E21: 1
A22: financiele_situatie | B22: gevolgen_materieel | C22: Louter financieel gezien, zonder aanpassingen te hoeven doen aan het jaarlijks te besteden budget | D22: kan de vereniging een waardedaling van de beleggingen aan van ongeveer 25% | E22: 2 | F22: =D22 -> kan de vereniging een waardedaling van de beleggingen aan van ongeveer 25%
A23: financiele_situatie | B23: gevolgen_materieel | C23: Louter financieel gezien, zonder aanpassingen te hoeven doen aan het jaarlijks te besteden budget | D23: kan de vereniging een waardedaling van de beleggingen aan van wel zo'n 40% | E23: 3
A24: financiele_situatie | B24: huidige_samenstelling | C24: Het huidige vrij belegbare vermogen van de vereniging | D24: bestaat overwegend uit spaargeld en/of obligaties | E24: 0
A25: financiele_situatie | B25: huidige_samenstelling | C25: Het huidige vrij belegbare vermogen van de vereniging | D25: is belegd in een portefeuille aandelen en obligaties | E25: 0 | F25: =D25 -> is belegd in een portefeuille aandelen en obligaties
A26: financiele_situatie | B26: huidige_samenstelling | C26: Het huidige vrij belegbare vermogen van de vereniging | D26: is vooral belegd in aandelen en andere risicodragende beleggingen | E26: 0
A27: kennis_ervaring | B27: kennis_beleggen | C27: Mijn kennis van beleggen | D27: is beperkt, ik weet er weinig van | E27: 1
A28: kennis_ervaring | B28: kennis_beleggen | C28: Mijn kennis van beleggen | D28: is gemiddeld en ik volg af en toe het financiële nieuws | E28: 2 | F28: =D28 -> is gemiddeld en ik volg af en toe het financiële nieuws
A29: kennis_ervaring | B29: kennis_beleggen | C29: Mijn kennis van beleggen | D29: is uitgebreid en ik volg het financiële nieuws op de voet | E29: 3
A30: kennis_ervaring | B30: kennis_instrumenten | C30: Mijn kennis van beleggingsinstrumenten | D30: is beperkt, ik weet er weinig van | E30: 1
A31: kennis_ervaring | B31: kennis_instrumenten | C31: Mijn kennis van beleggingsinstrumenten | D31: is aanwezig, ik weet wat aandelen en obligaties zijn | E31: 2 | F31: =D31 -> is aanwezig, ik weet wat aandelen en obligaties zijn
A32: kennis_ervaring | B32: kennis_instrumenten | C32: Mijn kennis van beleggingsinstrumenten | D32: is aanwezig, ik weet wat aandelen, obligaties en alternatieve beleggingen zijn | E32: 3
A33: kennis_ervaring | B33: ervaring_beleggingsdienstverlening | C33: Met beleggingsdienstverlening | D33: heb ik geen ervaring | E33: 1
A34: kennis_ervaring | B34: ervaring_beleggingsdienstverlening | C34: Met beleggingsdienstverlening | D34: heb ik ervaring, vooral met beleggingsadvies en/of execution only | E34: 3
A35: kennis_ervaring | B35: ervaring_beleggingsdienstverlening | C35: Met beleggingsdienstverlening | D35: heb ik ervaring, vooral met vermogensbeheer | E35: 2 | F35: =D35 -> heb ik ervaring, vooral met vermogensbeheer
A36: kennis_ervaring | B36: ervaring_beleggen | C36: Mijn ervaring met beleggen | D36: Ik heb geen ervaring met beleggen | E36: 1
A37: kennis_ervaring | B37: ervaring_beleggen | C37: Mijn ervaring met beleggen | D37: is beperkt | E37: 2
A38: kennis_ervaring | B38: ervaring_beleggen | C38: Mijn ervaring met beleggen | D38: is ruim aanwezig | E38: 3 | F38: =D38 -> is ruim aanwezig
A39: risicobereidheid | B39: gevolgen_emotioneel | C39: Als het gaat om slechte beleggingsresultaten van de vereniging | D39: dat leidt naar verwachting meteen tot discussies over het beleggingsbeleid | E39: 1
A40: risicobereidheid | B40: gevolgen_emotioneel | C40: Als het gaat om slechte beleggingsresultaten van de vereniging | D40: is de vereniging bereid, op enig moment, ongeveer 25% waardedaling te accepteren | E40: 2 | F40: =D40 -> is de vereniging bereid, op enig moment, ongeveer 25% waardedaling te accepteren
A41: risicobereidheid | B41: gevolgen_emotioneel | C41: Als het gaat om slechte beleggingsresultaten van de vereniging | D41: is de vereniging bereid, op enig moment, ongeveer 40% waardedaling te accepteren | E41: 3
A42: risicobereidheid | B42: hoe_vaak | C42: De waarde van de beleggingen van de vereniging zal fluctueren. | D42: Wij checken het geregeld en zitten er bovenop | E42: 1 | F42: =D42 -> Wij checken het geregeld en zitten er bovenop
A43: risicobereidheid | B43: hoe_vaak | C43: De waarde van de beleggingen van de vereniging zal fluctueren. | D43: Wij wachten de kwartaalrapportage af | E43: 2
A44: risicobereidheid | B44: hoe_vaak | C44: De waarde van de beleggingen van de vereniging zal fluctueren. | D44: Wij kijken een keer per jaar en minder dan een keer per kwartaal | E44: 3
A45: risicobereidheid | B45: beleggingshorizon | C45: Wat betreft de beleggingshorizon is het volgende van toepassing: | D45: de beleggingen van de vereniging worden gedaan voor een jaar of vijf | E45: 1
A46: risicobereidheid | B46: beleggingshorizon | C46: Wat betreft de beleggingshorizon is het volgende van toepassing: | D46: de beleggingen van de vereniging kunnen wel wel tien jaar aangehouden worden en er zijn geen tussentijdse plannen mee | E46: 2 | F46: =D46 -> de beleggingen van de vereniging kunnen wel wel tien jaar aangehouden worden en er zijn geen tussentijdse plannen mee
A47: risicobereidheid | B47: beleggingshorizon | C47: Wat betreft de beleggingshorizon is het volgende van toepassing: | D47: de beleggingen van de vereniging worden gedaan voor een periode langer dan tien jaar | E47: 3
A48: risicobereidheid | B48: doel_niet_halen | C48: Als de beleggingsdoelstelling van de vereniging niet gehaald wordt | D48: Dat zou buitengewoon teleurstellend zijn | E48: 1
A49: risicobereidheid | B49: doel_niet_halen | C49: Als de beleggingsdoelstelling van de vereniging niet gehaald wordt | D49: Dat zou teleurstellend zijn | E49: 2
A50: risicobereidheid | B50: doel_niet_halen | C50: Als de beleggingsdoelstelling van de vereniging niet gehaald wordt | D50: Dat kan gebeuren, want beleggen gaat nu eenmaal gepaard met risico's | E50: 3 | F50: =D50 -> Dat kan gebeuren, want beleggen gaat nu eenmaal gepaard met risico's
A51: duurzaamheid | B51: duurzaamheid_nu | C51: In de samenstelling van de huidige beleggingsportefeuille van de vereniging | D51: speelt duurzaamheid geen rol want er zijn nog geen beleggingen | E51: 0
A52: duurzaamheid | B52: duurzaamheid_nu | C52: In de samenstelling van de huidige beleggingsportefeuille van de vereniging | D52: spelen duurzaamheidsaspecten geen bijzondere rol | E52: 0 | F52: =D52 -> spelen duurzaamheidsaspecten geen bijzondere rol
A53: duurzaamheid | B53: duurzaamheid_nu | C53: In de samenstelling van de huidige beleggingsportefeuille van de vereniging | D53: spelen duurzaamheidsaspecten een bijzondere rol | E53: 0
A54: duurzaamheid | B54: duurzaamheid_bavd | C54: Bij de samenstelling van de portefeuille bij B.A. van Doorn | D54: bestaan geen duurzaamheidsvoorkeuren | E54: 0 | F54: =D54 -> bestaan geen duurzaamheidsvoorkeuren
A55: duurzaamheid | B55: duurzaamheid_bavd | C55: Bij de samenstelling van de portefeuille bij B.A. van Doorn | D55: moet rekening gehouden worden met de belangrijkste nadelige effecten op duurzaamheidsfactoren zoals hierboven genoemd | E55: 0
A56: duurzaamheid | B56: duurzaamheid_percentage | C56: Wat betreft het gedeelte duurzame beleggingen in de portefeuille van de vereniging | D56: moet dit meer zijn dan een kwart | E56: 0 | F56: =D56 -> moet dit meer zijn dan een kwart
A57: duurzaamheid | B57: duurzaamheid_percentage | C57: Wat betreft het gedeelte duurzame beleggingen in de portefeuille van de vereniging | D57: moet dit meer zijn dan de helft | E57: 0
A58: duurzaamheid | B58: duurzaamheid_taxonomie | C58: Zogenaamde Europese Taxonomie-beleggingen | D58: zijn geen vereiste voor de invulling van de portefeuille | E58: 0 | F58: =D58 -> zijn geen vereiste voor de invulling van de portefeuille
A59: duurzaamheid | B59: duurzaamheid_taxonomie | C59: Zogenaamde Europese Taxonomie-beleggingen | D59: moeten meer dan 10% uitmaken van de portfeuille | E59: 0
A60: overig | B60: overig | C60: Wilt u een toelichting geven op overige zaken die niet aan de orde zijn gekomen? | D60: nee, dat is niet nodig | E60: 0 | F60: =D60 -> nee, dat is niet nodig
A61: overig | B61: overig | C61: Wilt u een toelichting geven op overige zaken die niet aan de orde zijn gekomen? | D61: ja graag - hieronder opent een tekstvakje waarin u een toelichting kunt schrijven | E61: 0
A62: private_beleggingen | B62: private_beleggingen | C62: Gegeven de genoemde mogelijke voor- en nadelen van private beleggingen | D62: stellen wij prijs op het opnemen van private beleggingen in de portefeuille van de vereniging | E62: 0 | F62: stellen wij prijs op het opnemen van private beleggingen in de portefeuille van de vereniging
A63: private_beleggingen | B63: private_beleggingen | C63: Gegeven de genoemde mogelijke voor- en nadelen van private beleggingen | D63: hebben wij geen interesse in private beleggingen voor de portefeuille van de vereniging | E63: 0

Sheet vragen_antwoorden_ve_en
A1: categorie | B1: onderwerp | C1: vraag | D1: antwoord | E1: punten | F1: selected
A2: beleggingsdoelstelling | B2: beleggingsdoelstelling | C2: The assets of the association are invested | D2: to pay for an expense in the foreseeable future - see also the input fields below | E2: 1
A3: beleggingsdoelstelling | B3: beleggingsdoelstelling | C3: The assets of the association are invested | D3: to preserve it for the most part | E3: 2
A4: beleggingsdoelstelling | B4: beleggingsdoelstelling | C4: The assets of the association are invested | D4: to invest it without much downside risk, with the chance of some growth. | E4: 3
A5: beleggingsdoelstelling | B5: beleggingsdoelstelling | C5: The assets of the association are invested | D5: to grow it in the longer term | E5: 4 | F5: =D5 -> to grow it in the longer term
A6: beleggingsdoelstelling | B6: beleggingsdoelstelling | C6: The assets of the association are invested | D6: to have a chance of achieving the highest result in the long term | E6: 5
A7: beleggingsdoelstelling | B7: beleggingsdoelstelling_toelichting | C7: Would you like to explain the investment objective of the association (for example, on the basis of an investment statute)? | D7: No, that is sufficiently expressed in the answer to the previous question | E7: 0 | F7: =D7 -> No, that is sufficiently expressed in the answer to the previous question
A8: beleggingsdoelstelling | B8: beleggingsdoelstelling_toelichting | C8: Would you like to explain the investment objective of the association (for example, on the basis of an investment statute)? | D8: Yes please - below a text box opens in which you can write an explanation | E8: 0
A9: financiele_situatie | B9: eigen_vermogen_omvang | C9: Equity is the value of the assets minus the debts, such as a loan. The association's equity | D9: is not sufficient to maintain the expected minimum cash flow | E9: 1 | F9: =D9 -> is not sufficient to maintain the expected minimum cash flow
A10: financiele_situatie | B10: eigen_vermogen_omvang | C10: Equity is the value of the assets minus the debts, such as a loan. The association's equity | D10: is sufficient to maintain the expected minimum cash flow | E10: 2
A11: financiele_situatie | B11: eigen_vermogen_omvang | C11: Equity is the value of the assets minus the debts, such as a loan. The association's equity | D11: far exceeds the expected minimum cash flow in the future | E11: 3
A12: financiele_situatie | B12: eigen_vermogen_liquiditeit | C12: The equity can be freely investable and/or invested in real estate or other assets that are less easily tradable. The free assets of the association | D12: is only free to invest to a limited extent and consists of loans, real estate and/or other assets that are less easily tradable | E12: 1
A13: financiele_situatie | B13: eigen_vermogen_liquiditeit | C13: The equity can be freely investable and/or invested in real estate or other assets that are less easily tradable. The free assets of the association | D13: is largely free to invest and partly consists of real estate and/or less easily tradable assets | E13: 2 | F13: =D13 -> is largely free to invest and partly consists of real estate and/or less easily tradable assets
A14: financiele_situatie | B14: eigen_vermogen_liquiditeit | C14: The equity can be freely investable and/or invested in real estate or other assets that are less easily tradable. The free assets of the association | D14: is free to invest | E14: 3
A15: financiele_situatie | B15: deel | C15: The part of the association's freely investable assets that will be managed by B.A. van Doorn | D15: is a quarter or less | E15: 3
A16: financiele_situatie | B16: deel | C16: The part of the association's freely investable assets that will be managed by B.A. van Doorn | D16: is about half | E16: 2 | F16: =D16 -> is about half
A17: financiele_situatie | B17: deel | C17: The part of the association's freely investable assets that will be managed by B.A. van Doorn | D17: more than half of the | E17: 1
A18: financiele_situatie | B18: inkomen | C18: The income of the association (such as from contributions, donations or subsidies) | D18: is insufficient to bear the costs of the association and annual withdrawals from the investments are necessary | E18: 1
A19: financiele_situatie | B19: inkomen | C19: The income of the association (such as from contributions, donations or subsidies) | D19: is sufficient to bear the costs, so that only occasional withdrawals from the portfolio are necessary | E19: 2
A20: financiele_situatie | B20: inkomen | C20: The income of the association (such as from contributions, donations or subsidies) | D20: is more than sufficient and the assets of the association can continue to grow, except for possibly. withdrawals for incidental expenses | E20: 3 | F20: =D20 -> is more than sufficient and the assets of the association can continue to grow, except for possibly. withdrawals for incidental expenses
A21: financiele_situatie | B21: gevolgen_materieel | C21: From a purely financial point of view, without having to make adjustments to the annual budget to be spent | D21: the association can only have a limited decrease in the value of the investments | E21: 1
A22: financiele_situatie | B22: gevolgen_materieel | C22: From a purely financial point of view, without having to make adjustments to the annual budget to be spent | D22: the association can handle a decrease in the value of the investments of approximately 25% | E22: 2 | F22: =D22 -> the association can handle a decrease in the value of the investments of approximately 25%
A23: financiele_situatie | B23: gevolgen_materieel | C23: From a purely financial point of view, without having to make adjustments to the annual budget to be spent | D23: the association can handle a decrease in the value of the investments of up to 40% | E23: 3
A24: financiele_situatie | B24: huidige_samenstelling | C24: The current freely investable assets of the association | D24: consists mainly of savings and/or bonds | E24: 0
A25: financiele_situatie | B25: huidige_samenstelling | C25: The current freely investable assets of the association | D25: is invested in a portfolio of equities and bonds | E25: 0 | F25: =D25 -> is invested in a portfolio of equities and bonds
A26: financiele_situatie | B26: huidige_samenstelling | C26: The current freely investable assets of the association | D26: is mainly invested in shares and other risk-bearing investments | E26: 0
A27: kennis_ervaring | B27: kennis_beleggen | C27: My knowledge of investing | D27: is limited, I know little about it | E27: 1
A28: kennis_ervaring | B28: kennis_beleggen | C28: My knowledge of investing | D28: is average and I occasionally follow the financial news | E28: 2 | F28: =D28 -> is average and I occasionally follow the financial news
A29: kennis_ervaring | B29: kennis_beleggen | C29: My knowledge of investing | D29: is extensive and I follow the financial news closely | E29: 3
A30: kennis_ervaring | B30: kennis_instrumenten | C30: My knowledge of investment instruments | D30: is limited, I know little about it | E30: 1
A31: kennis_ervaring | B31: kennis_instrumenten | C31: My knowledge of investment instruments | D31: is present, I know what stocks and bonds are | E31: 2 | F31: =D31 -> is present, I know what stocks and bonds are
A32: kennis_ervaring | B32: kennis_instrumenten | C32: My knowledge of investment instruments | D32: is present, I know what stocks, bonds and alternative investments are | E32: 3
A33: kennis_ervaring | B33: ervaring_beleggingsdienstverlening | C33: With investment services | D33: I have no experience | E33: 1
A34: kennis_ervaring | B34: ervaring_beleggingsdienstverlening | C34: With investment services | D34: I have experience, especially with investment advice and/or execution only | E34: 3
A35: kennis_ervaring | B35: ervaring_beleggingsdienstverlening | C35: With investment services | D35: I have experience, especially with asset management | E35: 2 | F35: =D35 -> I have experience, especially with asset management
A36: kennis_ervaring | B36: ervaring_beleggen | C36: My experience with investing | D36: I have no experience with investing | E36: 1
A37: kennis_ervaring | B37: ervaring_beleggen | C37: My experience with investing | D37: is limited | E37: 2
A38: kennis_ervaring | B38: ervaring_beleggen | C38: My experience with investing | D38: is widely available | E38: 3 | F38: =D38 -> is widely available
A39: risicobereidheid | B39: gevolgen_emotioneel | C39: When it comes to poor investment results of the association | D39: This is expected to lead to discussions about the investment policy immediately | E39: 1
A40: risicobereidheid | B40: gevolgen_emotioneel | C40: When it comes to poor investment results of the association | D40: is the association prepared, at any time, to accept about a 25% decrease in value | E40: 2 | F40: =D40 -> is the association prepared, at any time, to accept about a 25% decrease in value
A41: risicobereidheid | B41: gevolgen_emotioneel | C41: When it comes to poor investment results of the association | D41: is the association prepared, at any time, to accept about 40% decrease in value | E41: 3
A42: risicobereidheid | B42: hoe_vaak | C42: The value of the association's investments will fluctuate. | D42: We check it regularly and are on top of it | E42: 1 | F42: =D42 -> We check it regularly and are on top of it
A43: risicobereidheid | B43: hoe_vaak | C43: The value of the association's investments will fluctuate. | D43: We await the quarterly report | E43: 2
A44: risicobereidheid | B44: hoe_vaak | C44: The value of the association's investments will fluctuate. | D44: We watch once a year and less than once a quarter | E44: 3
A45: risicobereidheid | B45: beleggingshorizon | C45: With regard to the investment horizon, the following applies: | D45: The investments of the association are made for about five years | E45: 1
A46: risicobereidheid | B46: beleggingshorizon | C46: With regard to the investment horizon, the following applies: | D46: The investments of the association can be held for up to ten years and there are no interim plans | E46: 2 | F46: =D46 -> The investments of the association can be held for up to ten years and there are no interim plans
A47: risicobereidheid | B47: beleggingshorizon | C47: With regard to the investment horizon, the following applies: | D47: The investments of the association are made for a period of more than ten years | E47: 3
A48: risicobereidheid | B48: doel_niet_halen | C48: If the investment objective of the association is not achieved | D48: That would be extremely disappointing | E48: 1
A49: risicobereidheid | B49: doel_niet_halen | C49: If the investment objective of the association is not achieved | D49: That would be disappointing | E49: 2
A50: risicobereidheid | B50: doel_niet_halen | C50: If the investment objective of the association is not achieved | D50: That can happen, because investing is associated with risks | E50: 3 | F50: =D50 -> That can happen, because investing is associated with risks
A51: duurzaamheid | B51: duurzaamheid_nu | C51: In the composition of the association's current investment portfolio | D51: sustainability does not play a role because there are no investments yet | E51: 0
A52: duurzaamheid | B52: duurzaamheid_nu | C52: In the composition of the association's current investment portfolio | D52: sustainability aspects do not play a special role | E52: 0 | F52: =D52 -> sustainability aspects do not play a special role
A53: duurzaamheid | B53: duurzaamheid_nu | C53: In the composition of the association's current investment portfolio | D53: sustainability aspects play a particular role in the | E53: 0
A54: duurzaamheid | B54: duurzaamheid_bavd | C54: In the composition of the portfolio at B.A. van Doorn | D54: there are no sustainability preferences | E54: 0 | F54: =D54 -> there are no sustainability preferences
A55: duurzaamheid | B55: duurzaamheid_bavd | C55: In the composition of the portfolio at B.A. van Doorn | D55: the principal adverse impacts on sustainability factors as mentioned above should be taken into account | E55: 0
A56: duurzaamheid | B56: duurzaamheid_percentage | C56: Regarding the sustainable investments part of the association's portfolio | D56: this must be more than a quarter | E56: 0 | F56: =D56 -> this must be more than a quarter
A57: duurzaamheid | B57: duurzaamheid_percentage | C57: Regarding the sustainable investments part of the association's portfolio | D57: this must be more than half | E57: 0
A58: duurzaamheid | B58: duurzaamheid_taxonomie | C58: So-called European Taxonomy investments | D58: are not a requirement for the completion of the portfolio | E58: 0 | F58: =D58 -> are not a requirement for the completion of the portfolio
A59: duurzaamheid | B59: duurzaamheid_taxonomie | C59: So-called European Taxonomy investments | D59: must account for more than 10% of the portfolio | E59: 0
A60: overig | B60: overig | C60: Would you like to explain other matters that have not been discussed? | D60: No, that's not necessary | E60: 0 | F60: =D60 -> No, that's not necessary
A61: overig | B61: overig | C61: Would you like to explain other matters that have not been discussed? | D61: Yes please - below a text box opens in which you can write an explanation | E61: 0
A62: private_beleggingen | B62: private_beleggingen | C62: Given the possible advantages and disadvantages of private investments mentioned, | D62: we would appreciate the inclusion of private investments in the portfolio of the association | E62: 0 | F62: =D62 -> we would appreciate the inclusion of private investments in the portfolio of the association
A63: private_beleggingen | B63: private_beleggingen | C63: Given the possible advantages and disadvantages of private investments mentioned, | D63: we are not interested in private investments for the portfolio of the association | E63: 0

Sheet vragen_antwoorden_st_backup
A1: categorie | B1: onderwerp | C1: vraag | D1: antwoord | E1: punten | F1: selected
A2: beleggingsdoelstelling | B2: beleggingsdoelstelling | C2: Het vermogen van de stichting wordt belegd | D2: om hiermee binnen afzienbare tijd een uitgave te betalen - zie ook de invulvelden hieronder | E2: 1
A3: beleggingsdoelstelling | B3: beleggingsdoelstelling | C3: Het vermogen van de stichting wordt belegd | D3: om het grotendeels in stand te houden | E3: 2
A4: beleggingsdoelstelling | B4: beleggingsdoelstelling | C4: Het vermogen van de stichting wordt belegd | D4: om het zonder veel neerwaarts risico te beleggen, met kans op enige groei. | E4: 3
A5: beleggingsdoelstelling | B5: beleggingsdoelstelling | C5: Het vermogen van de stichting wordt belegd | D5: om het te laten groeien op de langere termijn | E5: 4 | F5: =D5 -> om het te laten groeien op de langere termijn
A6: beleggingsdoelstelling | B6: beleggingsdoelstelling | C6: Het vermogen van de stichting wordt belegd | D6: om op de lange termijn kans te hebben op het hoogste resultaat | E6: 5
A7: beleggingsdoelstelling | B7: beleggingsdoelstelling_toelichting | C7: Wilt u een toelichting geven op de beleggingsdoelstelling van de stichting (bijvoorbeeld aan de hand van een beleggingsstatuut)? | D7: nee, dat is in het antwoord op de vorige vraag voldoende verwoord | E7: 0 | F7: =D7 -> nee, dat is in het antwoord op de vorige vraag voldoende verwoord
A8: beleggingsdoelstelling | B8: beleggingsdoelstelling_toelichting | C8: Wilt u een toelichting geven op de beleggingsdoelstelling van de stichting (bijvoorbeeld aan de hand van een beleggingsstatuut)? | D8: ja graag - hieronder opent een tekstvakje waarin u een toelichting kunt schrijven | E8: 0
A9: financiele_situatie | B9: eigen_vermogen_omvang | C9: Eigen vermogen is de waarde van de bezittingen minus de schulden, zoals een lening. Het eigen vermogen van de stichting | D9: is niet voldoende om de verwachte minimale kasstroom te kunnen handhaven | E9: 1 | F9: =D9 -> is niet voldoende om de verwachte minimale kasstroom te kunnen handhaven
A10: financiele_situatie | B10: eigen_vermogen_omvang | C10: Eigen vermogen is de waarde van de bezittingen minus de schulden, zoals een lening. Het eigen vermogen van de stichting | D10: is voldoende om de verwachte minimale kasstroom te handhaven | E10: 2
A11: financiele_situatie | B11: eigen_vermogen_omvang | C11: Eigen vermogen is de waarde van de bezittingen minus de schulden, zoals een lening. Het eigen vermogen van de stichting | D11: overstijgt ruimschoots de verwachte minimale kasstroom in de toekomst | E11: 3
A12: financiele_situatie | B12: eigen_vermogen_liquiditeit | C12: Het eigen vermogen kan vrij belegbaar zijn en/of belegd zijn in vastgoed of andere minder makkelijk verhandelbare vermogensbestanddelen. Het vrije vermogen van de stichting | D12: is slechts beperkt vrij te beleggen en bestaat uit verstrekte leningen, vastgoed en/of andere minder makkelijk verhandelbare vermogensbestanddelen | E12: 1
A13: financiele_situatie | B13: eigen_vermogen_liquiditeit | C13: Het eigen vermogen kan vrij belegbaar zijn en/of belegd zijn in vastgoed of andere minder makkelijk verhandelbare vermogensbestanddelen. Het vrije vermogen van de stichting | D13: is grotendeels vrij te beleggen en bestaat deels uit vastgoed en/of minder makkelijk verhandelbare vermogensbestanddelen | E13: 2 | F13: =D13 -> is grotendeels vrij te beleggen en bestaat deels uit vastgoed en/of minder makkelijk verhandelbare vermogensbestanddelen
A14: financiele_situatie | B14: eigen_vermogen_liquiditeit | C14: Het eigen vermogen kan vrij belegbaar zijn en/of belegd zijn in vastgoed of andere minder makkelijk verhandelbare vermogensbestanddelen. Het vrije vermogen van de stichting | D14: is vrij te beleggen | E14: 3
A15: financiele_situatie | B15: deel | C15: Het deel van het vrij belegbare vermogen van de stichting dat bij B.A. van Doorn in beheer komt | D15: is een kwart of minder | E15: 3
A16: financiele_situatie | B16: deel | C16: Het deel van het vrij belegbare vermogen van de stichting dat bij B.A. van Doorn in beheer komt | D16: is ongeveer de helft | E16: 2 | F16: =D16 -> is ongeveer de helft
A17: financiele_situatie | B17: deel | C17: Het deel van het vrij belegbare vermogen van de stichting dat bij B.A. van Doorn in beheer komt | D17: is meer dan de helft | E17: 1
A18: financiele_situatie | B18: inkomen | C18: Het inkomen van de stichting (zoals uit contributies, schenkingen of subsidies) | D18: is onvoldoende om de kosten van de stichting te dragen en jaarlijkse onttrekkingen uit de beleggingen zijn noodzakelijk | E18: 1
A19: financiele_situatie | B19: inkomen | C19: Het inkomen van de stichting (zoals uit contributies, schenkingen of subsidies) | D19: is voldoende om de kosten te dragen, waardoor slechts incidenteel onttrekkingen uit de portefeuille noodzakelijk zijn | E19: 2
A20: financiele_situatie | B20: inkomen | C20: Het inkomen van de stichting (zoals uit contributies, schenkingen of subsidies) | D20: is meer dan voldoende en het vermogen van de stichting kan blijven groeien, behoudens evt. onttrekkingen voor incidentele uitgaven | E20: 3 | F20: =D20 -> is meer dan voldoende en het vermogen van de stichting kan blijven groeien, behoudens evt. onttrekkingen voor incidentele uitgaven
A21: financiele_situatie | B21: gevolgen_materieel | C21: Louter financieel gezien, zonder aanpassingen te hoeven doen aan het jaarlijks te besteden budget | D21: kan de stichting maar een beperkte waardedaling hebben van de beleggingen | E21: 1
A22: financiele_situatie | B22: gevolgen_materieel | C22: Louter financieel gezien, zonder aanpassingen te hoeven doen aan het jaarlijks te besteden budget | D22: kan de stichting een waardedaling van de beleggingen aan van ongeveer 25% | E22: 2 | F22: =D22 -> kan de stichting een waardedaling van de beleggingen aan van ongeveer 25%
A23: financiele_situatie | B23: gevolgen_materieel | C23: Louter financieel gezien, zonder aanpassingen te hoeven doen aan het jaarlijks te besteden budget | D23: kan de stichting een waardedaling van de beleggingen aan van wel zo'n 40% | E23: 3
A24: financiele_situatie | B24: huidige_samenstelling | C24: Het huidige vrij belegbare vermogen van de stichting | D24: bestaat overwegend uit spaargeld en/of obligaties | E24: 0
A25: financiele_situatie | B25: huidige_samenstelling | C25: Het huidige vrij belegbare vermogen van de stichting | D25: is belegd in een portefeuille aandelen en obligaties | E25: 0 | F25: =D25 -> is belegd in een portefeuille aandelen en obligaties
A26: financiele_situatie | B26: huidige_samenstelling | C26: Het huidige vrij belegbare vermogen van de stichting | D26: is vooral belegd in aandelen en andere risicodragende beleggingen | E26: 0
A27: kennis_ervaring | B27: kennis_beleggen | C27: Mijn kennis van beleggen | D27: is beperkt, ik weet er weinig van | E27: 1
A28: kennis_ervaring | B28: kennis_beleggen | C28: Mijn kennis van beleggen | D28: is gemiddeld en ik volg af en toe het financiële nieuws | E28: 2 | F28: =D28 -> is gemiddeld en ik volg af en toe het financiële nieuws
A29: kennis_ervaring | B29: kennis_beleggen | C29: Mijn kennis van beleggen | D29: is uitgebreid en ik volg het financiële nieuws op de voet | E29: 3
A30: kennis_ervaring | B30: kennis_instrumenten | C30: Mijn kennis van beleggingsinstrumenten | D30: is beperkt, ik weet er weinig van | E30: 1
A31: kennis_ervaring | B31: kennis_instrumenten | C31: Mijn kennis van beleggingsinstrumenten | D31: is aanwezig, ik weet wat aandelen en obligaties zijn | E31: 2 | F31: =D31 -> is aanwezig, ik weet wat aandelen en obligaties zijn
A32: kennis_ervaring | B32: kennis_instrumenten | C32: Mijn kennis van beleggingsinstrumenten | D32: is aanwezig, ik weet wat aandelen, obligaties en alternatieve beleggingen zijn | E32: 3
A33: kennis_ervaring | B33: ervaring_beleggingsdienstverlening | C33: Met beleggingsdienstverlening | D33: heb ik geen ervaring | E33: 1
A34: kennis_ervaring | B34: ervaring_beleggingsdienstverlening | C34: Met beleggingsdienstverlening | D34: heb ik ervaring, vooral met beleggingsadvies en/of execution only | E34: 3
A35: kennis_ervaring | B35: ervaring_beleggingsdienstverlening | C35: Met beleggingsdienstverlening | D35: heb ik ervaring, vooral met vermogensbeheer | E35: 2 | F35: =D35 -> heb ik ervaring, vooral met vermogensbeheer
A36: kennis_ervaring | B36: ervaring_beleggen | C36: Mijn ervaring met beleggen | D36: Ik heb geen ervaring met beleggen | E36: 1
A37: kennis_ervaring | B37: ervaring_beleggen | C37: Mijn ervaring met beleggen | D37: is beperkt | E37: 2
A38: kennis_ervaring | B38: ervaring_beleggen | C38: Mijn ervaring met beleggen | D38: is ruim aanwezig | E38: 3 | F38: =D38 -> is ruim aanwezig
A39: risicobereidheid | B39: gevolgen_emotioneel | C39: Als het gaat om slechte beleggingsresultaten van de stichting | D39: dat leidt naar verwachting meteen tot discussies over het beleggingsbeleid | E39: 1
A40: risicobereidheid | B40: gevolgen_emotioneel | C40: Als het gaat om slechte beleggingsresultaten van de stichting | D40: is de stichting bereid, op enig moment, ongeveer 25% waardedaling te accepteren | E40: 2 | F40: =D40 -> is de stichting bereid, op enig moment, ongeveer 25% waardedaling te accepteren
A41: risicobereidheid | B41: gevolgen_emotioneel | C41: Als het gaat om slechte beleggingsresultaten van de stichting | D41: is de stichting bereid, op enig moment, ongeveer 40% waardedaling te accepteren | E41: 3
A42: risicobereidheid | B42: hoe_vaak | C42: De waarde van de beleggingen van de stichting zal fluctueren. | D42: Wij checken het geregeld en zitten er bovenop | E42: 1 | F42: =D42 -> Wij checken het geregeld en zitten er bovenop
A43: risicobereidheid | B43: hoe_vaak | C43: De waarde van de beleggingen van de stichting zal fluctueren. | D43: Wij wachten de kwartaalrapportage af | E43: 2
A44: risicobereidheid | B44: hoe_vaak | C44: De waarde van de beleggingen van de stichting zal fluctueren. | D44: Wij kijken een keer per jaar en minder dan een keer per kwartaal | E44: 3
A45: risicobereidheid | B45: beleggingshorizon | C45: Wat betreft de beleggingshorizon is het volgende van toepassing: | D45: de beleggingen van de stichting worden gedaan voor een jaar of vijf | E45: 1
A46: risicobereidheid | B46: beleggingshorizon | C46: Wat betreft de beleggingshorizon is het volgende van toepassing: | D46: de beleggingen van de stichting kunnen wel tien jaar aangehouden worden en er zijn geen tussentijdse plannen mee | E46: 2 | F46: =D46 -> de beleggingen van de stichting kunnen wel tien jaar aangehouden worden en er zijn geen tussentijdse plannen mee
A47: risicobereidheid | B47: beleggingshorizon | C47: Wat betreft de beleggingshorizon is het volgende van toepassing: | D47: de beleggingen van de stichting worden gedaan voor een periode langer dan tien jaar | E47: 3
A48: risicobereidheid | B48: doel_niet_halen | C48: Als de beleggingsdoelstelling van de stichting niet gehaald wordt | D48: Dat zou buitengewoon teleurstellend zijn | E48: 1
A49: risicobereidheid | B49: doel_niet_halen | C49: Als de beleggingsdoelstelling van de stichting niet gehaald wordt | D49: Dat zou teleurstellend zijn | E49: 2
A50: risicobereidheid | B50: doel_niet_halen | C50: Als de beleggingsdoelstelling van de stichting niet gehaald wordt | D50: Dat kan gebeuren, want beleggen gaat nu eenmaal gepaard met risico's | E50: 3 | F50: =D50 -> Dat kan gebeuren, want beleggen gaat nu eenmaal gepaard met risico's
A51: visueel | B51: visuele_keuze1 | C51: Welke figuur spreekt u in eerste instantie het meest aan? | D51: De linker illustratie | E51: 0 | F51: De linker illustratie
A52: visueel | B52: visuele_keuze1 | C52: Welke figuur spreekt u in eerste instantie het meest aan? | D52: De rechter illustratie | E52: 0
A53: visueel | B53: visuele_keuze2 | C53: Spreekt een van beide alternatieven u meer aan dan uw keuze op de vorige pagina? | D53: Nee, ik blijf bij mijn vorige keuze (de illustratie in het midden) | E53: 0 | F53: Nee, ik blijf bij mijn vorige keuze (de illustratie in het midden)
A54: visueel | B54: visuele_keuze2 | C54: Spreekt een van beide alternatieven u meer aan dan uw keuze op de vorige pagina? | D54: De illustratie links spreekt mij meer aan | E54: 0
A55: visueel | B55: visuele_keuze2 | C55: Spreekt een van beide alternatieven u meer aan dan uw keuze op de vorige pagina? | D55: De illustratie rechts spreekt mij meer aan | E55: 0
A56: duurzaamheid | B56: duurzaamheid_nu | C56: In de samenstelling van de huidige beleggingsportefeuille van de stichting | D56: speelt duurzaamheid geen rol want er zijn nog geen beleggingen | E56: 0
A57: duurzaamheid | B57: duurzaamheid_nu | C57: In de samenstelling van de huidige beleggingsportefeuille van de stichting | D57: spelen duurzaamheidsaspecten geen bijzondere rol | E57: 0 | F57: =D57 -> spelen duurzaamheidsaspecten geen bijzondere rol
A58: duurzaamheid | B58: duurzaamheid_nu | C58: In de samenstelling van de huidige beleggingsportefeuille van de stichting | D58: spelen duurzaamheidsaspecten een bijzondere rol | E58: 0
A59: duurzaamheid | B59: duurzaamheid_bavd | C59: Bij de samenstelling van de portefeuille bij B.A. van Doorn | D59: bestaan geen duurzaamheidsvoorkeuren | E59: 0 | F59: =D59 -> bestaan geen duurzaamheidsvoorkeuren
A60: duurzaamheid | B60: duurzaamheid_bavd | C60: Bij de samenstelling van de portefeuille bij B.A. van Doorn | D60: moet rekening gehouden worden met de belangrijkste nadelige effecten op duurzaamheidsfactoren zoals hierboven genoemd | E60: 0
A61: duurzaamheid | B61: duurzaamheid_percentage | C61: Wat betreft het gedeelte duurzame beleggingen in de portefeuille van de stichting | D61: moet dit meer zijn dan een kwart | E61: 0 | F61: =D61 -> moet dit meer zijn dan een kwart
A62: duurzaamheid | B62: duurzaamheid_percentage | C62: Wat betreft het gedeelte duurzame beleggingen in de portefeuille van de stichting | D62: moet dit meer zijn dan de helft | E62: 0
A63: duurzaamheid | B63: duurzaamheid_taxonomie | C63: Zogenaamde Europese Taxonomie-beleggingen | D63: zijn geen vereiste voor de invulling van de portefeuille | E63: 0 | F63: =D63 -> zijn geen vereiste voor de invulling van de portefeuille
A64: duurzaamheid | B64: duurzaamheid_taxonomie | C64: Zogenaamde Europese Taxonomie-beleggingen | D64: moeten meer dan 10% uitmaken van de portfeuille | E64: 0
A65: overig | B65: overig | C65: Wilt u een toelichting geven op overige zaken die niet aan de orde zijn gekomen? | D65: nee, dat is niet nodig | E65: 0 | F65: =D65 -> nee, dat is niet nodig
A66: overig | B66: overig | C66: Wilt u een toelichting geven op overige zaken die niet aan de orde zijn gekomen? | D66: ja graag - hieronder opent een tekstvakje waarin u een toelichting kunt schrijven | E66: 0

Sheet vragen_antwoorden_ov_backup
A1: categorie | B1: onderwerp | C1: vraag | D1: antwoord | E1: punten | F1: selected
A2: beleggingsdoelstelling | B2: beleggingsdoelstelling | C2: Het vermogen van de organisatie wordt belegd | D2: om hiermee binnen afzienbare tijd een uitgave te betalen - zie ook de invulvelden hieronder | E2: 1
A3: beleggingsdoelstelling | B3: beleggingsdoelstelling | C3: Het vermogen van de organisatie wordt belegd | D3: om het grotendeels in stand te houden | E3: 2
A4: beleggingsdoelstelling | B4: beleggingsdoelstelling | C4: Het vermogen van de organisatie wordt belegd | D4: om het zonder veel neerwaarts risico te beleggen, met kans op enige groei. | E4: 3
A5: beleggingsdoelstelling | B5: beleggingsdoelstelling | C5: Het vermogen van de organisatie wordt belegd | D5: om het te laten groeien op de langere termijn | E5: 4 | F5: =D5 -> om het te laten groeien op de langere termijn
A6: beleggingsdoelstelling | B6: beleggingsdoelstelling | C6: Het vermogen van de organisatie wordt belegd | D6: om op de lange termijn kans te hebben op het hoogste resultaat | E6: 5
A7: beleggingsdoelstelling | B7: beleggingsdoelstelling_toelichting | C7: Wilt u een toelichting geven op de beleggingsdoelstelling van de organisatie (bijvoorbeeld aan de hand van een beleggingsstatuut)? | D7: nee, dat is in het antwoord op de vorige vraag voldoende verwoord | E7: 0 | F7: =D7 -> nee, dat is in het antwoord op de vorige vraag voldoende verwoord
A8: beleggingsdoelstelling | B8: beleggingsdoelstelling_toelichting | C8: Wilt u een toelichting geven op de beleggingsdoelstelling van de organisatie (bijvoorbeeld aan de hand van een beleggingsstatuut)? | D8: ja graag - hieronder opent een tekstvakje waarin u een toelichting kunt schrijven | E8: 0
A9: financiele_situatie | B9: eigen_vermogen_omvang | C9: Eigen vermogen is de waarde van de bezittingen minus de schulden, zoals een lening. Het eigen vermogen van de organisatie | D9: is niet voldoende om de verwachte minimale kasstroom te kunnen handhaven | E9: 1 | F9: =D9 -> is niet voldoende om de verwachte minimale kasstroom te kunnen handhaven
A10: financiele_situatie | B10: eigen_vermogen_omvang | C10: Eigen vermogen is de waarde van de bezittingen minus de schulden, zoals een lening. Het eigen vermogen van de organisatie | D10: is voldoende om de verwachte minimale kasstroom te handhaven | E10: 2
A11: financiele_situatie | B11: eigen_vermogen_omvang | C11: Eigen vermogen is de waarde van de bezittingen minus de schulden, zoals een lening. Het eigen vermogen van de organisatie | D11: overstijgt ruimschoots de verwachte minimale kasstroom in de toekomst | E11: 3
A12: financiele_situatie | B12: eigen_vermogen_liquiditeit | C12: Het eigen vermogen kan vrij belegbaar zijn en/of belegd zijn in vastgoed of andere minder makkelijk verhandelbare vermogensbestanddelen. Het vrije vermogen van de organisatie | D12: is slechts beperkt vrij te beleggen en bestaat uit verstrekte leningen, vastgoed en/of andere minder makkelijk verhandelbare vermogensbestanddelen | E12: 1
A13: financiele_situatie | B13: eigen_vermogen_liquiditeit | C13: Het eigen vermogen kan vrij belegbaar zijn en/of belegd zijn in vastgoed of andere minder makkelijk verhandelbare vermogensbestanddelen. Het vrije vermogen van de organisatie | D13: is grotendeels vrij te beleggen en bestaat deels uit vastgoed en/of minder makkelijk verhandelbare vermogensbestanddelen | E13: 2 | F13: =D13 -> is grotendeels vrij te beleggen en bestaat deels uit vastgoed en/of minder makkelijk verhandelbare vermogensbestanddelen
A14: financiele_situatie | B14: eigen_vermogen_liquiditeit | C14: Het eigen vermogen kan vrij belegbaar zijn en/of belegd zijn in vastgoed of andere minder makkelijk verhandelbare vermogensbestanddelen. Het vrije vermogen van de organisatie | D14: is vrij te beleggen | E14: 3
A15: financiele_situatie | B15: deel | C15: Het deel van het vrij belegbare vermogen van de organisatie dat bij B.A. van Doorn in beheer komt | D15: is een kwart of minder | E15: 3
A16: financiele_situatie | B16: deel | C16: Het deel van het vrij belegbare vermogen van de organisatie dat bij B.A. van Doorn in beheer komt | D16: is ongeveer de helft | E16: 2 | F16: =D16 -> is ongeveer de helft
A17: financiele_situatie | B17: deel | C17: Het deel van het vrij belegbare vermogen van de organisatie dat bij B.A. van Doorn in beheer komt | D17: is meer dan de helft | E17: 1
A18: financiele_situatie | B18: inkomen | C18: Het inkomen van de organisatie (zoals uit contributies, schenkingen of subsidies) | D18: is onvoldoende om de kosten van de organisatie te dragen en jaarlijkse onttrekkingen uit de beleggingen zijn noodzakelijk | E18: 1
A19: financiele_situatie | B19: inkomen | C19: Het inkomen van de organisatie (zoals uit contributies, schenkingen of subsidies) | D19: is voldoende om de kosten te dragen, waardoor slechts incidenteel onttrekkingen uit de portefeuille noodzakelijk zijn | E19: 2
A20: financiele_situatie | B20: inkomen | C20: Het inkomen van de organisatie (zoals uit contributies, schenkingen of subsidies) | D20: is meer dan voldoende en het vermogen van de organisatie kan blijven groeien, behoudens evt. onttrekkingen voor incidentele uitgaven | E20: 3 | F20: =D20 -> is meer dan voldoende en het vermogen van de organisatie kan blijven groeien, behoudens evt. onttrekkingen voor incidentele uitgaven
A21: financiele_situatie | B21: gevolgen_materieel | C21: Louter financieel gezien, zonder aanpassingen te hoeven doen aan het jaarlijks te besteden budget | D21: kan de organisatie maar een beperkte waardedaling hebben van de beleggingen | E21: 1
A22: financiele_situatie | B22: gevolgen_materieel | C22: Louter financieel gezien, zonder aanpassingen te hoeven doen aan het jaarlijks te besteden budget | D22: kan de organisatie een waardedaling van de beleggingen aan van ongeveer 25% | E22: 2 | F22: =D22 -> kan de organisatie een waardedaling van de beleggingen aan van ongeveer 25%
A23: financiele_situatie | B23: gevolgen_materieel | C23: Louter financieel gezien, zonder aanpassingen te hoeven doen aan het jaarlijks te besteden budget | D23: kan de organisatie een waardedaling van de beleggingen aan van wel zo'n 40% | E23: 3
A24: financiele_situatie | B24: huidige_samenstelling | C24: Het huidige vrij belegbare vermogen van de organisatie | D24: bestaat overwegend uit spaargeld en/of obligaties | E24: 0
A25: financiele_situatie | B25: huidige_samenstelling | C25: Het huidige vrij belegbare vermogen van de organisatie | D25: is belegd in een portefeuille aandelen en obligaties | E25: 0 | F25: =D25 -> is belegd in een portefeuille aandelen en obligaties
A26: financiele_situatie | B26: huidige_samenstelling | C26: Het huidige vrij belegbare vermogen van de organisatie | D26: is vooral belegd in aandelen en andere risicodragende beleggingen | E26: 0
A27: kennis_ervaring | B27: kennis_beleggen | C27: Mijn kennis van beleggen | D27: is beperkt, ik weet er weinig van | E27: 1
A28: kennis_ervaring | B28: kennis_beleggen | C28: Mijn kennis van beleggen | D28: is gemiddeld en ik volg af en toe het financiële nieuws | E28: 2 | F28: =D28 -> is gemiddeld en ik volg af en toe het financiële nieuws
A29: kennis_ervaring | B29: kennis_beleggen | C29: Mijn kennis van beleggen | D29: is uitgebreid en ik volg het financiële nieuws op de voet | E29: 3
A30: kennis_ervaring | B30: kennis_instrumenten | C30: Mijn kennis van beleggingsinstrumenten | D30: is beperkt, ik weet er weinig van | E30: 1
A31: kennis_ervaring | B31: kennis_instrumenten | C31: Mijn kennis van beleggingsinstrumenten | D31: is aanwezig, ik weet wat aandelen en obligaties zijn | E31: 2 | F31: =D31 -> is aanwezig, ik weet wat aandelen en obligaties zijn
A32: kennis_ervaring | B32: kennis_instrumenten | C32: Mijn kennis van beleggingsinstrumenten | D32: is aanwezig, ik weet wat aandelen, obligaties en alternatieve beleggingen zijn | E32: 3
A33: kennis_ervaring | B33: ervaring_beleggingsdienstverlening | C33: Met beleggingsdienstverlening | D33: heb ik geen ervaring | E33: 1
A34: kennis_ervaring | B34: ervaring_beleggingsdienstverlening | C34: Met beleggingsdienstverlening | D34: heb ik ervaring, vooral met beleggingsadvies en/of execution only | E34: 3
A35: kennis_ervaring | B35: ervaring_beleggingsdienstverlening | C35: Met beleggingsdienstverlening | D35: heb ik ervaring, vooral met vermogensbeheer | E35: 2 | F35: =D35 -> heb ik ervaring, vooral met vermogensbeheer
A36: kennis_ervaring | B36: ervaring_beleggen | C36: Mijn ervaring met beleggen | D36: Ik heb geen ervaring met beleggen | E36: 1
A37: kennis_ervaring | B37: ervaring_beleggen | C37: Mijn ervaring met beleggen | D37: is beperkt | E37: 2
A38: kennis_ervaring | B38: ervaring_beleggen | C38: Mijn ervaring met beleggen | D38: is ruim aanwezig | E38: 3 | F38: =D38 -> is ruim aanwezig
A39: risicobereidheid | B39: gevolgen_emotioneel | C39: Als het gaat om slechte beleggingsresultaten van de organisatie | D39: dat leidt naar verwachting meteen tot discussies over het beleggingsbeleid | E39: 1
A40: risicobereidheid | B40: gevolgen_emotioneel | C40: Als het gaat om slechte beleggingsresultaten van de organisatie | D40: is de organisatie bereid, op enig moment, ongeveer 25% waardedaling te accepteren | E40: 2 | F40: =D40 -> is de organisatie bereid, op enig moment, ongeveer 25% waardedaling te accepteren
A41: risicobereidheid | B41: gevolgen_emotioneel | C41: Als het gaat om slechte beleggingsresultaten van de organisatie | D41: is de organisatie bereid, op enig moment, ongeveer 40% waardedaling te accepteren | E41: 3
A42: risicobereidheid | B42: hoe_vaak | C42: De waarde van de beleggingen van de organisatie zal fluctueren. | D42: Wij checken het geregeld en zitten er bovenop | E42: 1 | F42: =D42 -> Wij checken het geregeld en zitten er bovenop
A43: risicobereidheid | B43: hoe_vaak | C43: De waarde van de beleggingen van de organisatie zal fluctueren. | D43: Wij wachten de kwartaalrapportage af | E43: 2
A44: risicobereidheid | B44: hoe_vaak | C44: De waarde van de beleggingen van de organisatie zal fluctueren. | D44: Wij kijken een keer per jaar en minder dan een keer per kwartaal | E44: 3
A45: risicobereidheid | B45: beleggingshorizon | C45: Wat betreft de beleggingshorizon is het volgende van toepassing: | D45: de beleggingen van de organisatie worden gedaan voor een jaar of vijf | E45: 1
A46: risicobereidheid | B46: beleggingshorizon | C46: Wat betreft de beleggingshorizon is het volgende van toepassing: | D46: de beleggingen van de organisatie kunnen wel tien jaar aangehouden worden en er zijn geen tussentijdse plannen mee | E46: 2 | F46: =D46 -> de beleggingen van de organisatie kunnen wel tien jaar aangehouden worden en er zijn geen tussentijdse plannen mee
A47: risicobereidheid | B47: beleggingshorizon | C47: Wat betreft de beleggingshorizon is het volgende van toepassing: | D47: de beleggingen van de organisatie worden gedaan voor een periode langer dan tien jaar | E47: 3
A48: risicobereidheid | B48: doel_niet_halen | C48: Als de beleggingsdoelstelling van de organisatie niet gehaald wordt | D48: Dat zou buitengewoon teleurstellend zijn | E48: 1
A49: risicobereidheid | B49: doel_niet_halen | C49: Als de beleggingsdoelstelling van de organisatie niet gehaald wordt | D49: Dat zou teleurstellend zijn | E49: 2
A50: risicobereidheid | B50: doel_niet_halen | C50: Als de beleggingsdoelstelling van de organisatie niet gehaald wordt | D50: Dat kan gebeuren, want beleggen gaat nu eenmaal gepaard met risico's | E50: 3 | F50: =D50 -> Dat kan gebeuren, want beleggen gaat nu eenmaal gepaard met risico's
A51: visueel | B51: visuele_keuze1 | C51: Welke figuur spreekt u in eerste instantie het meest aan? | D51: De linker illustratie | E51: 0 | F51: De linker illustratie
A52: visueel | B52: visuele_keuze1 | C52: Welke figuur spreekt u in eerste instantie het meest aan? | D52: De rechter illustratie | E52: 0
A53: visueel | B53: visuele_keuze2 | C53: Spreekt een van beide alternatieven u meer aan dan uw keuze op de vorige pagina? | D53: Nee, ik blijf bij mijn vorige keuze (de illustratie in het midden) | E53: 0 | F53: Nee, ik blijf bij mijn vorige keuze (de illustratie in het midden)
A54: visueel | B54: visuele_keuze2 | C54: Spreekt een van beide alternatieven u meer aan dan uw keuze op de vorige pagina? | D54: De illustratie links spreekt mij meer aan | E54: 0
A55: visueel | B55: visuele_keuze2 | C55: Spreekt een van beide alternatieven u meer aan dan uw keuze op de vorige pagina? | D55: De illustratie rechts spreekt mij meer aan | E55: 0
A56: duurzaamheid | B56: duurzaamheid_nu | C56: In de samenstelling van de huidige beleggingsportefeuille van de organisatie | D56: speelt duurzaamheid geen rol want er zijn nog geen beleggingen | E56: 0
A57: duurzaamheid | B57: duurzaamheid_nu | C57: In de samenstelling van de huidige beleggingsportefeuille van de organisatie | D57: spelen duurzaamheidsaspecten geen bijzondere rol | E57: 0 | F57: =D57 -> spelen duurzaamheidsaspecten geen bijzondere rol
A58: duurzaamheid | B58: duurzaamheid_nu | C58: In de samenstelling van de huidige beleggingsportefeuille van de organisatie | D58: spelen duurzaamheidsaspecten een bijzondere rol | E58: 0
A59: duurzaamheid | B59: duurzaamheid_bavd | C59: Bij de samenstelling van de portefeuille bij B.A. van Doorn | D59: bestaan geen duurzaamheidsvoorkeuren | E59: 0 | F59: =D59 -> bestaan geen duurzaamheidsvoorkeuren
A60: duurzaamheid | B60: duurzaamheid_bavd | C60: Bij de samenstelling van de portefeuille bij B.A. van Doorn | D60: moet rekening gehouden worden met de belangrijkste nadelige effecten op duurzaamheidsfactoren zoals hierboven genoemd | E60: 0
A61: duurzaamheid | B61: duurzaamheid_percentage | C61: Wat betreft het gedeelte duurzame beleggingen in de portefeuille van de organisatie | D61: moet dit meer zijn dan een kwart | E61: 0 | F61: =D61 -> moet dit meer zijn dan een kwart
A62: duurzaamheid | B62: duurzaamheid_percentage | C62: Wat betreft het gedeelte duurzame beleggingen in de portefeuille van de organisatie | D62: moet dit meer zijn dan de helft | E62: 0
A63: duurzaamheid | B63: duurzaamheid_taxonomie | C63: Zogenaamde Europese Taxonomie-beleggingen | D63: zijn geen vereiste voor de invulling van de portefeuille | E63: 0 | F63: =D63 -> zijn geen vereiste voor de invulling van de portefeuille
A64: duurzaamheid | B64: duurzaamheid_taxonomie | C64: Zogenaamde Europese Taxonomie-beleggingen | D64: moeten meer dan 10% uitmaken van de portfeuille | E64: 0
A65: overig | B65: overig | C65: Wilt u een toelichting geven op overige zaken die niet aan de orde zijn gekomen? | D65: nee, dat is niet nodig | E65: 0 | F65: =D65 -> nee, dat is niet nodig
A66: overig | B66: overig | C66: Wilt u een toelichting geven op overige zaken die niet aan de orde zijn gekomen? | D66: ja graag - hieronder opent een tekstvakje waarin u een toelichting kunt schrijven | E66: 0

Sheet vertaaltabel
A1: beleggingsdoelstelling | B1: financiele_situatie | C1: kennis_ervaring | D1: risicobereidheid | E1: grafieken | F1: profiel
A2: 1 | B2: 6 | C2: 4 | D2: 5 | E2: 1 | F2: RM100
A3: 1 | B3: =B2+1 -> 7 | C3: =C2+(12-4)/12 -> 4.6666667 | D3: =D2+(15-5)/12 -> 5.8333333 | E3: 1 | F3: RM100 | I3: beleggingsdoelstelling | N3: financiele_situatie | S3: risicobereidheid | X3: kennis_ervaring
A4: 2 | B4: =B3+1 -> 8 | C4: =C3+(12-4)/12 -> 5.3333333 | D4: =D3+(15-5)/12 -> 6.6666667 | E4: 2 | F4: RD30RM70 | H4: punten | I4: profiel_nieuw | J4: profiel_oud | K4: nieuw profiel is | M4: punten | N4: profiel_nieuw | O4: profiel_oud | P4: nieuw profiel is | R4: punten | S4: profiel_nieuw | T4: profiel_oud | U4: nieuw profiel is | W4: punten | X4: profiel_nieuw | Y4: profiel_oud | Z4: nieuw profiel is
A5: 2 | B5: =B4+1 -> 9 | C5: =C4+(12-4)/12 -> 6 | D5: =D4+(15-5)/12 -> 7.5 | E5: 2 | F5: RD30RM70 | H5: 1 | I5: RM100 | J5: RM100 | K5: gelijk | M5: 6 | N5: RM100 | O5: RM100 | P5: gelijk | R5: 5 | S5: RM100 | T5: RM100 | U5: gelijk | W5: 4 | X5: RM100 | Y5: RM100 | Z5: gelijk
A6: 2 | B6: =B5+1 -> 10 | C6: =C5+(12-4)/12 -> 6.6666667 | D6: =D5+(15-5)/12 -> 8.3333333 | E6: 2 | F6: RD30RM70 | H6: 2 | I6: RD30RM70 | J6: RD30RM70 | K6: gelijk | M6: 7 | N6: RM100 | O6: RM100 | P6: gelijk | R6: 6 | S6: RM100 | T6: RD30RM70 | U6: conservatiever | W6: 5 | X6: RM100 | Y6: RD30RM70 | Z6: conservatiever
A7: 3 | B7: =B6+1 -> 11 | C7: =C6+(12-4)/12 -> 7.3333333 | D7: =D6+(15-5)/12 -> 9.1666667 | E7: 3 | F7: RD50RM50 | H7: 3 | I7: RD50RM50 | J7: RD50RM50 | K7: gelijk | M7: 8 | N7: RM100 | O7: RD30RM70 | P7: conservatiever | R7: 7 | S7: RD30RM70 | T7: RD30RM70 | U7: gelijk | W7: 6 | X7: RD30RM70 | Y7: RD30RM70 | Z7: gelijk
A8: 3 | B8: =B7+1 -> 12 | C8: =C7+(12-4)/12 -> 8 | D8: =D7+(15-5)/12 -> 10 | E8: 3 | F8: RD50RM50 | H8: 4 | I8: RD70RM30 | J8: RD70RM30 | K8: gelijk | M8: 9 | N8: RD30RM70 | O8: RD30RM70 | P8: gelijk | R8: 8 | S8: RD30RM70 | T8: RD30RM70 | U8: gelijk | W8: 7 | X8: RD30RM70 | Y8: RD50RM50 | Z8: conservatiever
A9: 3 | B9: =B8+1 -> 13 | C9: =C8+(12-4)/12 -> 8.6666667 | D9: =D8+(15-5)/12 -> 10.833333 | E9: 3 | F9: RD50RM50 | H9: 5 | I9: RD100 | J9: RD100 | K9: gelijk | M9: 10 | N9: RD30RM70 | O9: RD30RM70 | P9: gelijk | R9: 9 | S9: RD50RM50 | T9: RD50RM50 | U9: gelijk | W9: 8 | X9: RD50RM50 | Y9: RD50RM50 | Z9: gelijk
A10: 4 | B10: =B9+1 -> 14 | C10: =C9+(12-4)/12 -> 9.3333333 | D10: =D9+(15-5)/12 -> 11.666667 | E10: 4 | F10: RD70RM30 | M10: 11 | N10: RD50RM50 | O10: RD50RM50 | P10: gelijk | R10: 10 | S10: RD50RM50 | T10: RD50RM50 | U10: gelijk | W10: 9 | X10: RD70RM30 | Y10: RD70RM30 | Z10: gelijk
A11: 4 | B11: =B10+1 -> 15 | C11: =C10+(12-4)/12 -> 10 | D11: =D10+(15-5)/12 -> 12.5 | E11: 4 | F11: RD70RM30 | M11: 12 | N11: RD50RM50 | O11: RD50RM50 | P11: gelijk | R11: 11 | S11: RD70RM30 | T11: RD70RM30 | U11: gelijk | W11: 10 | X11: RD70RM30 | Y11: RD70RM30 | Z11: gelijk
A12: 4 | B12: =B11+1 -> 16 | C12: =C11+(12-4)/12 -> 10.666667 | D12: =D11+(15-5)/12 -> 13.333333 | E12: 4 | F12: RD70RM30 | M12: 13 | N12: RD50RM50 | O12: RD50RM50 | P12: gelijk | R12: 12 | S12: RD70RM30 | T12: RD70RM30 | U12: gelijk | W12: 11 | X12: RD100 | Y12: RD100 | Z12: gelijk
A13: 5 | B13: =B12+1 -> 17 | C13: =C12+(12-4)/12 -> 11.333333 | D13: =D12+(15-5)/12 -> 14.166667 | E13: 5 | F13: RD100 | M13: 14 | N13: RD70RM30 | O13: RD70RM30 | P13: gelijk | R13: 13 | S13: RD100 | T13: RD70RM30 | U13: minder conservatief | W13: 12 | X13: RD100 | Y13: RD100 | Z13: gelijk
A14: 5 | B14: =B13+1 -> 18 | C14: 12 | D14: 15 | E14: 5 | F14: RD100 | M14: 15 | N14: RD70RM30 | O14: RD70RM30 | P14: gelijk | R14: 14 | S14: RD100 | T14: RD100 | U14: gelijk
A15: deze tabel wordt niet meer gebruikt | M15: 16 | N15: RD100 | O15: RD70RM30 | P15: minder conservatief | R15: 15 | S15: RD100 | T15: RD100 | U15: gelijk
M16: 17 | N16: RD100 | O16: RD100 | P16: gelijk
M17: 18 | N17: RD100 | O17: RD100 | P17: gelijk

Sheet Sheet1
F3: chat gpt
E5: Q | F5: generate questions that test someone's investment risk aversion
E6: 1 | F6: How do you typically react when you see a sudden drop in the value of your investments?
E7: 2 | F7: What is the maximum percentage loss you are willing to accept on your investments before you become uncomfortable?
E8: 3 | F8: How do you feel about investing a significant portion of your portfolio in high-risk, high-reward assets such as cryptocurrencies or startup companies?
E9: 4 | F9: Do you prefer to invest in safe and stable assets such as bonds, or do you prefer to take on more risk for the potential of higher returns?
E10: 5 | F10: How would you feel if you lost 20% of your investment portfolio in a single year?
E11: 6 | F11: How important is it to you to have a diversified portfolio, and how much of your portfolio do you typically allocate to safer assets such as cash or bonds?
E12: 7 | F12: How comfortable are you with investing in emerging markets, where political instability or economic factors could potentially cause significant fluctuations in the value of your investments?
E13: 8 | F13: If you were presented with two investment options - one with a guaranteed return of 5% and another with a potential return of 10% but with a higher level of risk - which one would you choose and why?
E14: 9 | F14: Have you ever experienced a significant loss on an investment, and if so, how did you react and what did you learn from the experience?
E15: 10 | F15: How do you typically decide on the appropriate level of risk for your investments, and what factors do you consider in making that decision?
F19: generate multiple choice (3 choices) questions that test someones investment risk aversion
F21: Which of the following best describes your attitude towards risk when it comes to investing?
F22: A) I am willing to take on a significant amount of risk for the potential of higher returns.
F23: B) I prefer to strike a balance between risk and reward.
F24: C) I prioritize the preservation of my capital over the potential for high returns.
F26: If you saw a sudden drop in the value of your investments, what would you do?
F27: A) Sell all of my investments immediately to avoid further losses.
F28: B) Wait and see if the market recovers before making any decisions.
F29: C) Buy more of the same investment in hopes that it will eventually bounce back.
F31: Which type of investment would you be most comfortable with?
F32: A) A high-risk, high-reward investment such as a speculative stock or cryptocurrency.
F33: B) A moderately risky investment such as a diversified mutual fund or exchange-traded fund.
... F44: C) I focus on low-risk investments in order to preserve my capital and minimize losses.

Sheet geschrapte vragen
A1: risicobereidheid | B1: doel_niet_halen | C1: Als ik mijn beleggingsdoelstelling niet haal | D1: Dan moet ik mijn levensstandaard daaraan aanpassen | E1: 1
A2: risicobereidheid | B2: doel_niet_halen | C2: Als ik mijn beleggingsdoelstelling niet haal | D2: Dit heeft nauwelijk consquenties voor mijn levensstandaard | E2: 2 | F2: Dit heeft nauwelijk consquenties voor mijn levensstandaard
A3: risicobereidheid | B3: doel_niet_halen | C3: Als ik mijn beleggingsdoelstelling niet haal | D3: Dat heeft geen enkele invloed want ik heb voldoende reserves | E3: 3
A7: uit de bv geschrapt
A8: financiele_situatie | B8: eigen_vermogen_omvang | C8: Eigen vermogen is de waarde van de bezittingen inclusief verstrekte leningen, minus de schulden, zoals een opgenomen lening. Het vrije vermogen in de besloten vennootschap | D8: is niet voldoende om de verwachte minimale kasstroom te kunnen handhaven | E8: 1 | F8: =D8 -> is niet voldoende om de verwachte minimale kasstroom te kunnen handhaven
A9: financiele_situatie | B9: eigen_vermogen_omvang | C9: Eigen vermogen is de waarde van de bezittingen inclusief verstrekte leningen, minus de schulden, zoals een opgenomen lening. Het vrije vermogen in de besloten vennootschap | D9: is voldoende om de verwachte minimale kasstroom te handhaven | E9: 2
A10: financiele_situatie | B10: eigen_vermogen_omvang | C10: Eigen vermogen is de waarde van de bezittingen inclusief verstrekte leningen, minus de schulden, zoals een opgenomen lening. Het vrije vermogen in de besloten vennootschap | D10: overstijgt ruimschoots de verwachte minimale kasstroom in de toekomst | E10: 3
A12: financiele_situatie | B12: inkomen | C12: Mijn inkomen in privé (zoals uit loon, pensioen, of onderneming) | D12: is onvoldoende om van te leven en ik moet periodiek onttrekkingen doen uit de besloten vennootschap | E12: 1
A13: financiele_situatie | B13: inkomen | C13: Mijn inkomen in privé (zoals uit loon, pensioen, of onderneming) | D13: is genoeg om van te leven, waardoor ik slechts incidenteel onttrekkingen hoef te doen uit de besloten vennootschap | E13: 2
A14: financiele_situatie | B14: inkomen | C14: Mijn inkomen in privé (zoals uit loon, pensioen, of onderneming) | D14: is meer dan voldoende en het vermogen in de besloten vennootschap kan blijven groeien, behoudens evt. onttrekkingen voor het betalen van belasting | E14: 3 | F14: =D14 -> is meer dan voldoende en het vermogen in de besloten vennootschap kan blijven groeien, behoudens evt. onttrekkingen voor het betalen van belasting
A17: uit alle entiteiten op 16juni 22
A18: risicobereidheid | B18: maximaal_verlies | C18: Het verlies dat acceptabel is binnen de termijn van de beleggingshorizon | D18: is minder dan 5% | E18: 1
A19: risicobereidheid | B19: maximaal_verlies | C19: Het verlies dat acceptabel is binnen de termijn van de beleggingshorizon | D19: is minder dan 20% | E19: 2 | F19: =D19 -> is minder dan 20%
A20: risicobereidheid | B20: maximaal_verlies | C20: Het verlies dat acceptabel is binnen de termijn van de beleggingshorizon | D20: is minder dan 40% | E20: 3
